Workbook
Name Slicer_Category: #N/A
Name Slicer_Employee_Name: #N/A
Name Slicer_PaymentMethod: #N/A
Name Slicer_Region: #N/A

Sheet Orders
A1: OrderID | B1: OrderDate | C1: CustomerID | D1: Customer Name | E1: ProductID | F1: Product Name | G1: EmployeeID | H1: Employee Name | I1: Category | J1: Region | K1: Selling Price | L1: Quantity | M1: Discount | N1: Total amount | O1: Revenue | P1: ShipDate | Q1: PaymentMethod | R1: Data Issue
A2: O0001 | B2: 45738 | C2: C042 | D2: Meera Kumar | E2: P028 | F2: =VLOOKUP(Orders!E2,Products!A:F,2,FALSE) -> Football | G2: E04 | H2: =VLOOKUP(G2,Employees!A:E,2,FALSE) -> Fatima Sheikh | I2: =VLOOKUP(E2,Products!A:F,3,FALSE) -> Sports | J2: North | K2: =VLOOKUP(E2,Products!A:F,5,FALSE) -> 3493.54 | L2: 1 | M2: 0.1 | N2: =K2*L2 -> 3493.54 | O2: =N2*(1-M2) -> 3144.186 | P2: 2025-03-31 | Q2: Cash on Delivery | R2: =IF(L2=0,"Missing Quantity","")
A3: O0002 | B3: 45733 | C3: C029 | D3: Pooja Kumar | E3: P016 | F3: =VLOOKUP(Orders!E3,Products!A:F,2,FALSE) -> LED Lamp | G3: E01 | H3: =VLOOKUP(G3,Employees!A:E,2,FALSE) -> Karan Mehta | I3: =VLOOKUP(E3,Products!A:F,3,FALSE) -> Home & Kitchen | J3: South | K3: =VLOOKUP(E3,Products!A:F,5,FALSE) -> 3772.12 | L3: 2 | M3: 0.15 | N3: =K3*L3 -> 7544.24 | O3: =N3*(1-M3) -> 6412.604 | P3: 2025-03-23 | Q3: Credit Card | R3: =IF(L3=0,"Missing Quantity","")
A4: O0003 | B4: 45599 | C4: C013 | D4: Kavya Sharma | E4: P014 | F4: =VLOOKUP(Orders!E4,Products!A:F,2,FALSE) -> Blender | G4: E04 | H4: =VLOOKUP(G4,Employees!A:E,2,FALSE) -> Fatima Sheikh | I4: =VLOOKUP(E4,Products!A:F,3,FALSE) -> Home & Kitchen | J4: South | K4: =VLOOKUP(E4,Products!A:F,5,FALSE) -> 733.33 | L4: 9 | M4: 0 | N4: =K4*L4 -> 6599.97 | O4: =N4*(1-M4) -> 6599.97 | P4: 2024-11-10 | Q4: Debit Card | R4: =IF(L4=0,"Missing Quantity","")
A5: O0004 | B5: 45594 | C5: C044 | D5: Sanjay Desai | E5: P044 | F5: =VLOOKUP(Orders!E5,Products!A:F,2,FALSE) -> Cooking Oil 1L | G5: E03 | H5: =VLOOKUP(G5,Employees!A:E,2,FALSE) -> Rohit Sinha | I5: =VLOOKUP(E5,Products!A:F,3,FALSE) -> Grocery | J5: East | K5: =VLOOKUP(E5,Products!A:F,5,FALSE) -> 620.89 | L5: 9 | M5: 0 | N5: =K5*L5 -> 5588.01 | O5: =N5*(1-M5) -> 5588.01 | P5: 2024-11-02 | Q5: Debit Card | R5: =IF(L5=0,"Missing Quantity","")
A6: O0005 | B6: 45470 | C6: C021 | D6: Amit Kumar | E6: P041 | F6: =VLOOKUP(Orders!E6,Products!A:F,2,FALSE) -> Board Game | G6: E03 | H6: =VLOOKUP(G6,Employees!A:E,2,FALSE) -> Rohit Sinha | I6: =VLOOKUP(E6,Products!A:F,3,FALSE) -> Toys | J6: East | K6: =VLOOKUP(E6,Products!A:F,5,FALSE) -> 136.91 | L6: 10 | M6: 0.1 | N6: =K6*L6 -> 1369.1 | O6: =N6*(1-M6) -> 1232.19 | P6: 2024-07-02 | Q6: Net Banking | R6: =IF(L6=0,"Missing Quantity","")
A7: O0006 | B7: 45292 | C7: C021 | D7: Amit Kumar | E7: P026 | F7: =VLOOKUP(Orders!E7,Products!A:F,2,FALSE) -> Dumbbell Set | G7: E09 | H7: =VLOOKUP(G7,Employees!A:E,2,FALSE) -> Rajesh Iyer | I7: =VLOOKUP(E7,Products!A:F,3,FALSE) -> Sports | J7: East | K7: =VLOOKUP(E7,Products!A:F,5,FALSE) -> 973.21 | L7: 5 | M7: 0 | N7: =K7*L7 -> 4866.05 | O7: =N7*(1-M7) -> 4866.05 | P7: 2024-01-05 | Q7: Net Banking | R7: =IF(L7=0,"Missing Quantity","")
A8: O0007 | B8: 45621 | C8: C040 | D8: Aarav Kumar | E8: P048 | F8: =VLOOKUP(Orders!E8,Products!A:F,2,FALSE) -> Spice Combo | G8: E04 | H8: =VLOOKUP(G8,Employees!A:E,2,FALSE) -> Fatima Sheikh | I8: =VLOOKUP(E8,Products!A:F,3,FALSE) -> Grocery | J8: North | K8: =VLOOKUP(E8,Products!A:F,5,FALSE) -> 2041.83 | L8: 8 | M8: 0.05 | N8: =K8*L8 -> 16334.64 | O8: =N8*(1-M8) -> 15517.908 | P8: 2024-12-03 | Q8: Net Banking | R8: =IF(L8=0,"Missing Quantity","")
A9: O0008 | B9: 45776 | C9: C041 | D9: Deepak Mehta | E9: P009 | F9: =VLOOKUP(Orders!E9,Products!A:F,2,FALSE) -> Hoodie | G9: E03 | H9: =VLOOKUP(G9,Employees!A:E,2,FALSE) -> Rohit Sinha | I9: =VLOOKUP(E9,Products!A:F,3,FALSE) -> Clothing | J9: South | K9: =VLOOKUP(E9,Products!A:F,5,FALSE) -> 3929.31 | L9: 3 | M9: 0.15 | N9: =K9*L9 -> 11787.93 | O9: =N9*(1-M9) -> 10019.74 | P9: 2025-05-01 | Q9: Net Banking | R9: =IF(L9=0,"Missing Quantity","")
A10: O0009 | B10: 45635 | C10: C032 | D10: Kavya Singh | E10: P016 | F10: =VLOOKUP(Orders!E10,Products!A:F,2,FALSE) -> LED Lamp | G10: E04 | H10: =VLOOKUP(G10,Employees!A:E,2,FALSE) -> Fatima Sheikh | I10: =VLOOKUP(E10,Products!A:F,3,FALSE) -> Home & Kitchen | J10: South | K10: =VLOOKUP(E10,Products!A:F,5,FALSE) -> 3772.12 | L10: 2 | M10: 0.2 | N10: =K10*L10 -> 7544.24 | O10: =N10*(1-M10) -> 6035.392 | P10: 2024-12-13 | Q10: UPI | R10: =IF(L10=0,"Missing Quantity","")
A11: O0010 | B11: 45495 | C11: C013 | D11: Kavya Sharma | E11: P028 | F11: =VLOOKUP(Orders!E11,Products!A:F,2,FALSE) -> Football | G11: E04 | H11: =VLOOKUP(G11,Employees!A:E,2,FALSE) -> Fatima Sheikh | I11: =VLOOKUP(E11,Products!A:F,3,FALSE) -> Sports | J11: North | K11: =VLOOKUP(E11,Products!A:F,5,FALSE) -> 3493.54 | L11: 3 | M11: 0 | N11: =K11*L11 -> 10480.62 | O11: =N11*(1-M11) -> 10480.62 | P11: 2024-07-23 | Q11: Debit Card | R11: =IF(L11=0,"Missing Quantity","")
A12: O0011 | B12: 45366 | C12: C008 | D12: Karan Verma | E12: P038 | F12: =VLOOKUP(Orders!E12,Products!A:F,2,FALSE) -> Remote Car | G12: E04 | H12: =VLOOKUP(G12,Employees!A:E,2,FALSE) -> Fatima Sheikh | I12: =VLOOKUP(E12,Products!A:F,3,FALSE) -> Toys | J12: North | K12: =VLOOKUP(E12,Products!A:F,5,FALSE) -> 3205.14 | L12: 8 | M12: 0.05 | N12: =K12*L12 -> 25641.12 | O12: =N12*(1-M12) -> 24359.064 | P12: 2024-03-25 | Q12: Debit Card | R12: =IF(L12=0,"Missing Quantity","")
A13: O0012 | B13: 45798 | C13: C017 | D13: Amit Shah | E13: P033 | F13: =VLOOKUP(Orders!E13,Products!A:F,2,FALSE) -> Cookbook | G13: E04 | H13: =VLOOKUP(G13,Employees!A:E,2,FALSE) -> Fatima Sheikh | I13: =VLOOKUP(E13,Products!A:F,3,FALSE) -> Books | J13: West | K13: =VLOOKUP(E13,Products!A:F,5,FALSE) -> 2316.2 | L13: 7 | M13: 0 | N13: =K13*L13 -> 16213.4 | O13: =N13*(1-M13) -> 16213.4 | P13: 2025-05-24 | Q13: Credit Card | R13: =IF(L13=0,"Missing Quantity","")
... A127: O0126 | B127: 45450 | C127: C027 | D127: Sneha Gupta | E127: P014 | F127: =VLOOKUP(Orders!E127,Products!A:F,2,FALSE) -> Blender | G127: E03 | H127: =VLOOKUP(G127,Employees!A:E,2,FALSE) -> Rohit Sinha | I127: =VLOOKUP(E127,Products!A:F,3,FALSE) -> Home & Kitchen | J127: East | K127: =VLOOKUP(E127,Products!A:F,5,FALSE) -> 733.33 | L127: 7 | M127: 0.15 | N127: =K127*L127 -> 5133.31 | O127: =N127*(1-M127) -> 4363.3135 | P127: 2024-06-09 | Q127: Net Banking | R127: =IF(L127=0,"Missing Quantity","")
A128: O0401 | B128: 45450 | C128: C027 | D128: Sneha Gupta | E128: P014 | F128: =VLOOKUP(Orders!E403,Products!A:F,2,FALSE) -> Formal Shirt | G128: E03 | H128: =VLOOKUP(G128,Employees!A:E,2,FALSE) -> Rohit Sinha | I128: =VLOOKUP(E128,Products!A:F,3,FALSE) -> Home & Kitchen | J128: East | K128: =VLOOKUP(E128,Products!A:F,5,FALSE) -> 733.33 | L128: 7 | M128: 0.15 | N128: =K128*L128 -> 5133.31 | O128: =N128*(1-M128) -> 4363.3135 | P128: 2024-06-09 | Q128: Net Banking | R128: =IF(L128=0,"Missing Quantity","")
A129: O0127 | B129: 45709 | C129: C012 | D129: Deepak Shah | E129: P006 | F129: =VLOOKUP(Orders!E128,Products!A:F,2,FALSE) -> Blender | G129: E03 | H129: =VLOOKUP(G129,Employees!A:E,2,FALSE) -> Rohit Sinha | I129: =VLOOKUP(E129,Products!A:F,3,FALSE) -> Electronics | J129: North | K129: =VLOOKUP(E129,Products!A:F,5,FALSE) -> 2779.58 | L129: 5 | M129: 0 | N129: =K129*L129 -> 13897.9 | O129: =N129*(1-M129) -> 13897.9 | P129: 2025-02-27 | Q129: Debit Card | R129: =IF(L129=0,"Missing Quantity","")
A130: O0128 | B130: 45747 | C130: C020 | D130: Priya Sharma | E130: P020 | F130: =VLOOKUP(Orders!E129,Products!A:F,2,FALSE) -> Power Bank | G130: E03 | H130: =VLOOKUP(G130,Employees!A:E,2,FALSE) -> Rohit Sinha | I130: =VLOOKUP(E130,Products!A:F,3,FALSE) -> Beauty | J130: West | K130: =VLOOKUP(E130,Products!A:F,5,FALSE) -> 2359.5 | L130: 4 | M130: 0.2 | N130: =K130*L130 -> 9438 | O130: =N130*(1-M130) -> 7550.4 | P130: 2025-04-06 | Q130: Cash on Delivery | R130: =IF(L130=0,"Missing Quantity","")
A131: O0129 | B131: 45659 | C131: C001 | D131: Yash Mehta | E131: P033 | F131: =VLOOKUP(Orders!E130,Products!A:F,2,FALSE) -> Moisturizer | G131: E01 | H131: =VLOOKUP(G131,Employees!A:E,2,FALSE) -> Karan Mehta | I131: =VLOOKUP(E131,Products!A:F,3,FALSE) -> Books | J131: North | K131: =VLOOKUP(E131,Products!A:F,5,FALSE) -> 2316.2 | L131: 1 | M131: 0.05 | N131: =K131*L131 -> 2316.2 | O131: =N131*(1-M131) -> 2200.39 | P131: 2025-01-07 | Q131: Credit Card | R131: =IF(L131=0,"Missing Quantity","")
A132: O0130 | B132: 45757 | C132: C006 | D132: Riya Mehta | E132: P033 | F132: =VLOOKUP(Orders!E131,Products!A:F,2,FALSE) -> Cookbook | G132: E03 | H132: =VLOOKUP(G132,Employees!A:E,2,FALSE) -> Rohit Sinha | I132: =VLOOKUP(E132,Products!A:F,3,FALSE) -> Books | J132: West | K132: =VLOOKUP(E132,Products!A:F,5,FALSE) -> 2316.2 | L132: 2 | M132: 0.15 | N132: =K132*L132 -> 4632.4 | O132: =N132*(1-M132) -> 3937.54 | P132: 2025-04-14 | Q132: Credit Card | R132: =IF(L132=0,"Missing Quantity","")
A133: O0131 | B133: 45633 | C133: C009 | D133: Ananya Gupta | E133: P011 | F133: =VLOOKUP(Orders!E132,Products!A:F,2,FALSE) -> Cookbook | G133: E03 | H133: =VLOOKUP(G133,Employees!A:E,2,FALSE) -> Rohit Sinha | I133: =VLOOKUP(E133,Products!A:F,3,FALSE) -> Clothing | J133: North | K133: =VLOOKUP(E133,Products!A:F,5,FALSE) -> 1309.58 | L133: 4 | M133: 0 | N133: =K133*L133 -> 5238.32 | O133: =N133*(1-M133) -> 5238.32 | P133: 2024-12-17 | Q133: Credit Card | R133: =IF(L133=0,"Missing Quantity","")
A134: O0132 | B134: 45504 | C134: C041 | D134: Deepak Mehta | E134: P006 | F134: =VLOOKUP(Orders!E133,Products!A:F,2,FALSE) -> Sports Jacket | G134: E01 | H134: =VLOOKUP(G134,Employees!A:E,2,FALSE) -> Karan Mehta | I134: =VLOOKUP(E134,Products!A:F,3,FALSE) -> Electronics | J134: South | K134: =VLOOKUP(E134,Products!A:F,5,FALSE) -> 2779.58 | L134: 10 | M134: 0 | N134: =K134*L134 -> 27795.8 | O134: =N134*(1-M134) -> 27795.8 | P134: 2024-08-04 | Q134: UPI | R134: =IF(L134=0,"Missing Quantity","")
A135: O0133 | B135: 45294 | C135: C050 | D135: Vivaan Sharma | E135: P025 | F135: =VLOOKUP(Orders!E134,Products!A:F,2,FALSE) -> Power Bank | G135: E09 | H135: =VLOOKUP(G135,Employees!A:E,2,FALSE) -> Rajesh Iyer | I135: =VLOOKUP(E135,Products!A:F,3,FALSE) -> Sports | J135: North | K135: =VLOOKUP(E135,Products!A:F,5,FALSE) -> 4703.04 | L135: 5 | M135: 0.2 | N135: =K135*L135 -> 23515.2 | O135: =N135*(1-M135) -> 18812.16 | P135: 2024-01-06 | Q135: Net Banking | R135: =IF(L135=0,"Missing Quantity","")
A136: O0134 | B136: 45548 | C136: C010 | D136: Aarav Singh | E136: P031 | F136: =VLOOKUP(Orders!E135,Products!A:F,2,FALSE) -> Yoga Mat | G136: E03 | H136: =VLOOKUP(G136,Employees!A:E,2,FALSE) -> Rohit Sinha | I136: =VLOOKUP(E136,Products!A:F,3,FALSE) -> Books | J136: North | K136: =VLOOKUP(E136,Products!A:F,5,FALSE) -> 2128.4 | L136: 3 | M136: 0 | N136: =K136*L136 -> 6385.2 | O136: =N136*(1-M136) -> 6385.2 | P136: 2024-09-14 | Q136: Credit Card | R136: =IF(L136=0,"Missing Quantity","")
A137: O0135 | B137: 45658 | C137: C030 | D137: Aditya Mehta | E137: P044 | F137: =VLOOKUP(Orders!E136,Products!A:F,2,FALSE) -> Novel - Fiction | G137: E02 | H137: =VLOOKUP(G137,Employees!A:E,2,FALSE) -> Priya Nair | I137: =VLOOKUP(E137,Products!A:F,3,FALSE) -> Grocery | J137: West | K137: =VLOOKUP(E137,Products!A:F,5,FALSE) -> 620.89 | L137: 4 | M137: 0.1 | N137: =K137*L137 -> 2483.56 | O137: =N137*(1-M137) -> 2235.204 | P137: 2025-01-07 | Q137: UPI | R137: =IF(L137=0,"Missing Quantity","")
A138: O0136 | B138: 45563 | C138: C047 | D138: Riya Joshi | E138: P045 | F138: =VLOOKUP(Orders!E137,Products!A:F,2,FALSE) -> Cooking Oil 1L | G138: E09 | H138: =VLOOKUP(G138,Employees!A:E,2,FALSE) -> Rajesh Iyer | I138: =VLOOKUP(E138,Products!A:F,3,FALSE) -> Grocery | J138: West | K138: =VLOOKUP(E138,Products!A:F,5,FALSE) -> 3576.75 | L138: 1 | M138: 0 | N138: =K138*L138 -> 3576.75 | O138: =N138*(1-M138) -> 3576.75 | P138: 2024-10-05 | Q138: Credit Card | R138: =IF(L138=0,"Missing Quantity","")
A139: O0137 | B139: 45779 | C139: C011 | D139: Aarav Patel | E139: P033 | F139: =VLOOKUP(Orders!E138,Products!A:F,2,FALSE) -> Green Tea Pack | G139: E04 | H139: =VLOOKUP(G139,Employees!A:E,2,FALSE) -> Fatima Sheikh | I139: =VLOOKUP(E139,Products!A:F,3,FALSE) -> Books | J139: West | K139: =VLOOKUP(E139,Products!A:F,5,FALSE) -> 2316.2 | L139: 8 | M139: 0.2 | N139: =K139*L139 -> 18529.6 | O139: =N139*(1-M139) -> 14823.68 | P139: 2025-05-08 | Q139: Debit Card | R139: =IF(L139=0,"Missing Quantity","")
A140: O0138 | B140: 45807 | C140: C059 | D140: Sakshi Gupta | E140: P036 | F140: =VLOOKUP(Orders!E139,Products!A:F,2,FALSE) -> Cookbook | G140: E01 | H140: =VLOOKUP(G140,Employees!A:E,2,FALSE) -> Karan Mehta | I140: =VLOOKUP(E140,Products!A:F,3,FALSE) -> Books | J140: South | K140: =VLOOKUP(E140,Products!A:F,5,FALSE) -> 2489.91 | L140: 4 | M140: 0.1 | N140: =K140*L140 -> 9959.64 | O140: =N140*(1-M140) -> 8963.676 | P140: 2025-05-31 | Q140: Debit Card | R140: =IF(L140=0,"Missing Quantity","")
... A331: O0329 | B331: 45308 | C331: C041 | D331: Deepak Mehta | E331: P040 | F331: =VLOOKUP(Orders!E330,Products!A:F,2,FALSE) -> Cricket Bat | G331: E04 | H331: =VLOOKUP(G331,Employees!A:E,2,FALSE) -> Fatima Sheikh | I331: =VLOOKUP(E331,Products!A:F,3,FALSE) -> Toys | J331: West | K331: =VLOOKUP(E331,Products!A:F,5,FALSE) -> 1212.79 | L331: 4 | M331: 0 | N331: =K331*L331 -> 4851.16 | O331: =N331*(1-M331) -> 4851.16 | P331: 2024-01-19 | Q331: Net Banking | R331: =IF(L331=0,"Missing Quantity","")
A332: O0402 | B332: 45308 | C332: C041 | D332: Deepak Mehta | E332: P040 | F332: =VLOOKUP(Orders!E404,Products!A:F,2,FALSE) -> Formal Shirt | G332: E04 | H332: =VLOOKUP(G332,Employees!A:E,2,FALSE) -> Fatima Sheikh | I332: =VLOOKUP(E332,Products!A:F,3,FALSE) -> Toys | J332: West | K332: =VLOOKUP(E332,Products!A:F,5,FALSE) -> 1212.79 | L332: 4 | M332: 0 | N332: =K332*L332 -> 4851.16 | O332: =N332*(1-M332) -> 4851.16 | P332: 2024-01-19 | Q332: Net Banking | R332: =IF(L332=0,"Missing Quantity","")
A333: O0330 | B333: 45326 | C333: C015 | D333: Simran Joshi | E333: P027 | F333: =VLOOKUP(Orders!E331,Products!A:F,2,FALSE) -> Soft Toy | G333: E01 | H333: =VLOOKUP(G333,Employees!A:E,2,FALSE) -> Karan Mehta | I333: =VLOOKUP(E333,Products!A:F,3,FALSE) -> Sports | J333: North | K333: =VLOOKUP(E333,Products!A:F,5,FALSE) -> 3128.51 | L333: 8 | M333: 0.1 | N333: =K333*L333 -> 25028.08 | O333: =N333*(1-M333) -> 22525.272 | P333: 2024-02-05 | Q333: Credit Card | R333: =IF(L333=0,"Missing Quantity","")
A334: O0331 | B334: 45703 | C334: C030 | D334: Aditya Mehta | E334: P015 | F334: =VLOOKUP(Orders!E332,Products!A:F,2,FALSE) -> Soft Toy | G334: E01 | H334: =VLOOKUP(G334,Employees!A:E,2,FALSE) -> Karan Mehta | I334: =VLOOKUP(E334,Products!A:F,3,FALSE) -> Home & Kitchen | J334: North | K334: =VLOOKUP(E334,Products!A:F,5,FALSE) -> 2849.53 | L334: 8 | M334: 0 | N334: =K334*L334 -> 22796.24 | O334: =N334*(1-M334) -> 22796.24 | P334: 2025-02-24 | Q334: Credit Card | R334: =IF(L334=0,"Missing Quantity","")
A335: O0332 | B335: 45435 | C335: C034 | D335: Sakshi Verma | E335: P004 | F335: =VLOOKUP(Orders!E333,Products!A:F,2,FALSE) -> Cricket Bat | G335: E04 | H335: =VLOOKUP(G335,Employees!A:E,2,FALSE) -> Fatima Sheikh | I335: =VLOOKUP(E335,Products!A:F,3,FALSE) -> Electronics | J335: South | K335: =VLOOKUP(E335,Products!A:F,5,FALSE) -> 2184.51 | L335: 9 | M335: 0 | N335: =K335*L335 -> 19660.59 | O335: =N335*(1-M335) -> 19660.59 | P335: 2024-05-27 | Q335: Net Banking | R335: =IF(L335=0,"Missing Quantity","")
A336: O0333 | B336: 45620 | C336: C015 | D336: Simran Joshi | E336: P002 | F336: =VLOOKUP(Orders!E334,Products!A:F,2,FALSE) -> Ceramic Mug Set | G336: E02 | H336: =VLOOKUP(G336,Employees!A:E,2,FALSE) -> Priya Nair | I336: =VLOOKUP(E336,Products!A:F,3,FALSE) -> Electronics | J336: North | K336: =VLOOKUP(E336,Products!A:F,5,FALSE) -> 991.59 | L336: 4 | M336: 0 | N336: =K336*L336 -> 3966.36 | O336: =N336*(1-M336) -> 3966.36 | P336: 2024-11-27 | Q336: Debit Card | R336: =IF(L336=0,"Missing Quantity","")
A337: O0334 | B337: 45599 | C337: C040 | D337: Aarav Kumar | E337: P042 | F337: =VLOOKUP(Orders!E335,Products!A:F,2,FALSE) -> Laptop Stand | G337: E02 | H337: =VLOOKUP(G337,Employees!A:E,2,FALSE) -> Priya Nair | I337: =VLOOKUP(E337,Products!A:F,3,FALSE) -> Toys | J337: North | K337: =VLOOKUP(E337,Products!A:F,5,FALSE) -> 4390.62 | L337: 5 | M337: 0 | N337: =K337*L337 -> 21953.1 | O337: =N337*(1-M337) -> 21953.1 | P337: 2024-11-12 | Q337: Debit Card | R337: =IF(L337=0,"Missing Quantity","")
A338: O0335 | B338: 45799 | C338: C036 | D338: Aarav Desai | E338: P015 | F338: =VLOOKUP(Orders!E336,Products!A:F,2,FALSE) -> Bluetooth Speaker | G338: E03 | H338: =VLOOKUP(G338,Employees!A:E,2,FALSE) -> Rohit Sinha | I338: =VLOOKUP(E338,Products!A:F,3,FALSE) -> Home & Kitchen | J338: South | K338: =VLOOKUP(E338,Products!A:F,5,FALSE) -> 2849.53 | L338: 1 | M338: 0 | N338: =K338*L338 -> 2849.53 | O338: =N338*(1-M338) -> 2849.53 | P338: 2025-05-29 | Q338: Debit Card | R338: =IF(L338=0,"Missing Quantity","")
A339: O0336 | B339: 45710 | C339: C030 | D339: Aditya Mehta | E339: P021 | F339: =VLOOKUP(Orders!E337,Products!A:F,2,FALSE) -> Action Figure | G339: E03 | H339: =VLOOKUP(G339,Employees!A:E,2,FALSE) -> Rohit Sinha | I339: =VLOOKUP(E339,Products!A:F,3,FALSE) -> Beauty | J339: North | K339: =VLOOKUP(E339,Products!A:F,5,FALSE) -> 1513.99 | L339: 3 | M339: 0 | N339: =K339*L339 -> 4541.97 | O339: =N339*(1-M339) -> 4541.97 | P339: 2025-03-01 | Q339: Net Banking | R339: =IF(L339=0,"Missing Quantity","")
A340: O0337 | B340: 45776 | C340: C037 | D340: Rohan Kumar | E340: P016 | F340: =VLOOKUP(Orders!E338,Products!A:F,2,FALSE) -> Ceramic Mug Set | G340: E04 | H340: =VLOOKUP(G340,Employees!A:E,2,FALSE) -> Fatima Sheikh | I340: =VLOOKUP(E340,Products!A:F,3,FALSE) -> Home & Kitchen | J340: South | K340: =VLOOKUP(E340,Products!A:F,5,FALSE) -> 3772.12 | L340: 4 | M340: 0.2 | N340: =K340*L340 -> 15088.48 | O340: =N340*(1-M340) -> 12070.784 | P340: 2025-05-03 | Q340: UPI | R340: =IF(L340=0,"Missing Quantity","")
A341: O0338 | B341: 45766 | C341: C030 | D341: Aditya Mehta | E341: P016 | F341: =VLOOKUP(Orders!E339,Products!A:F,2,FALSE) -> Lipstick | G341: E01 | H341: =VLOOKUP(G341,Employees!A:E,2,FALSE) -> Karan Mehta | I341: =VLOOKUP(E341,Products!A:F,3,FALSE) -> Home & Kitchen | J341: East | K341: =VLOOKUP(E341,Products!A:F,5,FALSE) -> 3772.12 | L341: 1 | M341: 0.1 | N341: =K341*L341 -> 3772.12 | O341: =N341*(1-M341) -> 3394.908 | P341: 2025-04-26 | Q341: Net Banking | R341: =IF(L341=0,"Missing Quantity","")
A342: O0339 | B342: 45834 | C342: C060 | D342: Anjali Patel | E342: P032 | F342: =VLOOKUP(Orders!E340,Products!A:F,2,FALSE) -> LED Lamp | G342: E04 | H342: =VLOOKUP(G342,Employees!A:E,2,FALSE) -> Fatima Sheikh | I342: =VLOOKUP(E342,Products!A:F,3,FALSE) -> Books | J342: South | K342: =VLOOKUP(E342,Products!A:F,5,FALSE) -> 605.26 | L342: 3 | M342: 0.05 | N342: =K342*L342 -> 1815.78 | O342: =N342*(1-M342) -> 1724.991 | P342: 2025-06-30 | Q342: UPI | R342: =IF(L342=0,"Missing Quantity","")
A343: O0340 | B343: 45630 | C343: C031 | D343: Sakshi Gupta | E343: P006 | F343: =VLOOKUP(Orders!E341,Products!A:F,2,FALSE) -> LED Lamp | G343: E09 | H343: =VLOOKUP(G343,Employees!A:E,2,FALSE) -> Rajesh Iyer | I343: =VLOOKUP(E343,Products!A:F,3,FALSE) -> Electronics | J343: West | K343: =VLOOKUP(E343,Products!A:F,5,FALSE) -> 2779.58 | L343: 2 | M343: 0.05 | N343: =K343*L343 -> 5559.16 | O343: =N343*(1-M343) -> 5281.202 | P343: 2024-12-10 | Q343: Net Banking | R343: =IF(L343=0,"Missing Quantity","")
A344: O0403 | B344: 45630 | C344: C031 | D344: Sakshi Gupta | E344: P006 | F344: =VLOOKUP(Orders!E405,Products!A:F,2,FALSE) -> Comic Book | G344: E09 | H344: =VLOOKUP(G344,Employees!A:E,2,FALSE) -> Rajesh Iyer | I344: =VLOOKUP(E344,Products!A:F,3,FALSE) -> Electronics | J344: West | K344: =VLOOKUP(E344,Products!A:F,5,FALSE) -> 2779.58 | L344: 2 | M344: 0.05 | N344: =K344*L344 -> 5559.16 | O344: =N344*(1-M344) -> 5281.202 | P344: 2024-12-10 | Q344: Net Banking | R344: =IF(L344=0,"Missing Quantity","")
A345: O0341 | B345: 45487 | C345: C008 | D345: Karan Verma | E345: P002 | F345: =VLOOKUP(Orders!E342,Products!A:F,2,FALSE) -> Self-Help Book | G345: E01 | H345: =VLOOKUP(G345,Employees!A:E,2,FALSE) -> Karan Mehta | I345: =VLOOKUP(E345,Products!A:F,3,FALSE) -> Electronics | J345: West | K345: =VLOOKUP(E345,Products!A:F,5,FALSE) -> 991.59 | L345: 1 | M345: 0 | N345: =K345*L345 -> 991.59 | O345: =N345*(1-M345) -> 991.59 | P345: 2024-07-21 | Q345: Credit Card | R345: =IF(L345=0,"Missing Quantity","")
A346: O0342 | B346: 45484 | C346: C044 | D346: Sanjay Desai | E346: P022 | F346: =VLOOKUP(Orders!E343,Products!A:F,2,FALSE) -> Power Bank | G346: E04 | H346: =VLOOKUP(G346,Employees!A:E,2,FALSE) -> Fatima Sheikh | I346: =VLOOKUP(E346,Products!A:F,3,FALSE) -> Beauty | J346: North | K346: =VLOOKUP(E346,Products!A:F,5,FALSE) -> 3414.07 | L346: 10 | M346: 0.15 | N346: =K346*L346 -> 34140.7 | O346: =N346*(1-M346) -> 29019.595 | P346: 2024-07-20 | Q346: Debit Card | R346: =IF(L346=0,"Missing Quantity","")
A347: O0343 | B347: 45505 | C347: C054 | D347: Simran Mehta | E347: P002 | F347: =VLOOKUP(Orders!E344,Products!A:F,2,FALSE) -> Power Bank | G347: E09 | H347: =VLOOKUP(G347,Employees!A:E,2,FALSE) -> Rajesh Iyer | I347: =VLOOKUP(E347,Products!A:F,3,FALSE) -> Electronics | J347: North | K347: =VLOOKUP(E347,Products!A:F,5,FALSE) -> 991.59 | L347: 6 | M347: 0 | N347: =K347*L347 -> 5949.54 | O347: =N347*(1-M347) -> 5949.54 | P347: 2024-08-02 | Q347: UPI | R347: =IF(L347=0,"Missing Quantity","")
A348: O0344 | B348: 45412 | C348: C048 | D348: Deepak Mehta | E348: P032 | F348: =VLOOKUP(Orders!E345,Products!A:F,2,FALSE) -> Bluetooth Speaker | G348: E04 | H348: =VLOOKUP(G348,Employees!A:E,2,FALSE) -> Fatima Sheikh | I348: =VLOOKUP(E348,Products!A:F,3,FALSE) -> Books | J348: North | K348: =VLOOKUP(E348,Products!A:F,5,FALSE) -> 605.26 | L348: 8 | M348: 0 | N348: =K348*L348 -> 4842.08 | O348: =N348*(1-M348) -> 4842.08 | P348: 2024-05-10 | Q348: Debit Card | R348: =IF(L348=0,"Missing Quantity","")
A349: O0345 | B349: 45537 | C349: C025 | D349: Aarav Joshi | E349: P024 | F349: =VLOOKUP(Orders!E346,Products!A:F,2,FALSE) -> Hair Serum | G349: E04 | H349: =VLOOKUP(G349,Employees!A:E,2,FALSE) -> Fatima Sheikh | I349: =VLOOKUP(E349,Products!A:F,3,FALSE) -> Beauty | J349: East | K349: =VLOOKUP(E349,Products!A:F,5,FALSE) -> 1140.8 | L349: 9 | M349: 0 | N349: =K349*L349 -> 10267.2 | O349: =N349*(1-M349) -> 10267.2 | P349: 2024-09-07 | Q349: Debit Card | R349: =IF(L349=0,"Missing Quantity","")
A350: O0346 | B350: 45659 | C350: C009 | D350: Ananya Gupta | E350: P009 | F350: =VLOOKUP(Orders!E347,Products!A:F,2,FALSE) -> Bluetooth Speaker | G350: E09 | H350: =VLOOKUP(G350,Employees!A:E,2,FALSE) -> Rajesh Iyer | I350: =VLOOKUP(E350,Products!A:F,3,FALSE) -> Clothing | J350: East | K350: =VLOOKUP(E350,Products!A:F,5,FALSE) -> 3929.31 | L350: 5 | M350: 0 | N350: =K350*L350 -> 19646.55 | O350: =N350*(1-M350) -> 19646.55 | P350: 2025-01-08 | Q350: Debit Card | R350: =IF(L350=0,"Missing Quantity","")
A351: O0347 | B351: 45392 | C351: C036 | D351: Aarav Desai | E351: P028 | F351: =VLOOKUP(Orders!E348,Products!A:F,2,FALSE) -> Self-Help Book | G351: E01 | H351: =VLOOKUP(G351,Employees!A:E,2,FALSE) -> Karan Mehta | I351: =VLOOKUP(E351,Products!A:F,3,FALSE) -> Sports | J351: North | K351: =VLOOKUP(E351,Products!A:F,5,FALSE) -> 3493.54 | L351: 8 | M351: 0.2 | N351: =K351*L351 -> 27948.32 | O351: =N351*(1-M351) -> 22358.656 | P351: 2024-04-16 | Q351: Cash on Delivery | R351: =IF(L351=0,"Missing Quantity","")
A352: O0348 | B352: 45612 | C352: C018 | D352: Meera Verma | E352: P008 | F352: =VLOOKUP(Orders!E349,Products!A:F,2,FALSE) -> Perfume | G352: E04 | H352: =VLOOKUP(G352,Employees!A:E,2,FALSE) -> Fatima Sheikh | I352: =VLOOKUP(E352,Products!A:F,3,FALSE) -> Clothing | J352: North | K352: =VLOOKUP(E352,Products!A:F,5,FALSE) -> 1498.91 | L352: 0 | M352: 0 | N352: =K352*L352 -> 0 | O352: =N352*(1-M352) -> 0 | P352: 2024-11-26 | Q352: UPI | R352: =IF(L352=0,"Missing Quantity","") -> Missing Quantity
A353: O0349 | B353: 45308 | C353: C036 | D353: Aarav Desai | E353: P022 | F353: =VLOOKUP(Orders!E350,Products!A:F,2,FALSE) -> Hoodie | G353: E02 | H353: =VLOOKUP(G353,Employees!A:E,2,FALSE) -> Priya Nair | I353: =VLOOKUP(E353,Products!A:F,3,FALSE) -> Beauty | J353: East | K353: =VLOOKUP(E353,Products!A:F,5,FALSE) -> 3414.07 | L353: 5 | M353: 0.1 | N353: =K353*L353 -> 17070.35 | O353: =N353*(1-M353) -> 15363.315 | P353: 2024-01-27 | Q353: Cash on Delivery | R353: =IF(L353=0,"Missing Quantity","")
A354: O0350 | B354: 45448 | C354: C041 | D354: Deepak Mehta | E354: P028 | F354: =VLOOKUP(Orders!E351,Products!A:F,2,FALSE) -> Football | G354: E04 | H354: =VLOOKUP(G354,Employees!A:E,2,FALSE) -> Fatima Sheikh | I354: =VLOOKUP(E354,Products!A:F,3,FALSE) -> Sports | J354: East | K354: =VLOOKUP(E354,Products!A:F,5,FALSE) -> 3493.54 | L354: 4 | M354: 0 | N354: =K354*L354 -> 13974.16 | O354: =N354*(1-M354) -> 13974.16 | P354: 2024-06-09 | Q354: Net Banking | R354: =IF(L354=0,"Missing Quantity","")
A355: O0351 | B355: 45543 | C355: C051 | D355: Deepak Verma | E355: P025 | F355: =VLOOKUP(Orders!E352,Products!A:F,2,FALSE) -> Denim Jeans | G355: E02 | H355: =VLOOKUP(G355,Employees!A:E,2,FALSE) -> Priya Nair | I355: =VLOOKUP(E355,Products!A:F,3,FALSE) -> Sports | J355: South | K355: =VLOOKUP(E355,Products!A:F,5,FALSE) -> 4703.04 | L355: 8 | M355: 0.1 | N355: =K355*L355 -> 37624.32 | O355: =N355*(1-M355) -> 33861.888 | P355: 2024-09-14 | Q355: Debit Card | R355: =IF(L355=0,"Missing Quantity","")
A356: O0352 | B356: 45794 | C356: C002 | D356: Pooja Shah | E356: P038 | F356: =VLOOKUP(Orders!E353,Products!A:F,2,FALSE) -> Hair Serum | G356: E09 | H356: =VLOOKUP(G356,Employees!A:E,2,FALSE) -> Rajesh Iyer | I356: =VLOOKUP(E356,Products!A:F,3,FALSE) -> Toys | J356: North | K356: =VLOOKUP(E356,Products!A:F,5,FALSE) -> 3205.14 | L356: 8 | M356: 0 | N356: =K356*L356 -> 25641.12 | O356: =N356*(1-M356) -> 25641.12 | P356: 2025-05-23 | Q356: UPI | R356: =IF(L356=0,"Missing Quantity","")
... A403: O0399 | B403: 45400 | C403: C027 | D403: Sneha Gupta | E403: P010 | F403: =VLOOKUP(Orders!E400,Products!A:F,2,FALSE) -> Moisturizer | G403: E01 | H403: =VLOOKUP(G403,Employees!A:E,2,FALSE) -> Karan Mehta | I403: =VLOOKUP(E403,Products!A:F,3,FALSE) -> Clothing | J403: North | K403: =VLOOKUP(E403,Products!A:F,5,FALSE) -> 1156.02 | L403: 1 | M403: 0 | N403: =K403*L403 -> 1156.02 | O403: =N403*(1-M403) -> 1156.02 | P403: 2024-04-23 | Q403: Net Banking | R403: =IF(L403=0,"Missing Quantity","")
A404: O0404 | B404: 45400 | C404: C027 | D404: Sneha Gupta | E404: P010 | F404: =VLOOKUP(Orders!E402,Products!A:F,2,FALSE) -> Sunscreen | G404: E01 | H404: =VLOOKUP(G404,Employees!A:E,2,FALSE) -> Karan Mehta | I404: =VLOOKUP(E404,Products!A:F,3,FALSE) -> Clothing | J404: North | K404: =VLOOKUP(E404,Products!A:F,5,FALSE) -> 1156.02 | L404: 1 | M404: 0 | N404: =K404*L404 -> 1156.02 | O404: =N404*(1-M404) -> 1156.02 | P404: 2024-04-23 | Q404: Net Banking | R404: =IF(L404=0,"Missing Quantity","")
A405: O0400 | B405: 45823 | C405: C018 | D405: Meera Verma | E405: P035 | F405: =VLOOKUP(Orders!E401,Products!A:F,2,FALSE) -> Soft Toy | G405: E04 | H405: =VLOOKUP(G405,Employees!A:E,2,FALSE) -> Fatima Sheikh | I405: =VLOOKUP(E405,Products!A:F,3,FALSE) -> Books | J405: North | K405: =VLOOKUP(E405,Products!A:F,5,FALSE) -> 1253.57 | L405: 9 | M405: 0.1 | N405: =K405*L405 -> 11282.13 | O405: =N405*(1-M405) -> 10153.917 | P405: 2025-06-25 | Q405: Debit Card | R405: =IF(L405=0,"Missing Quantity","")

Sheet Sheet2
A1: OrderID | B1: OrderDate | C1: CustomerID | D1: Customer Name | E1: ProductID | F1: Product Name | G1: EmployeeID | H1: Employee Name | I1: Region | J1: Selling Price | K1: Quantity | L1: Discount | M1: Total amount | N1: Revenue | O1: ShipDate | P1: PaymentMethod | Q1: Data Issue
A2: O0340 | B2: 2024-12-04 | C2: C031 | D2: Sakshi Gupta | E2: P006 | F2: Power Bank | G2: E09 | H2: Rajesh Iyer | I2: West | J2: 2779.58 | K2: 2 | L2: 0.05 | M2: 5559.16 | N2: 5281.202 | O2: 2024-12-10 | P2: Net Banking
A3: O0329 | B3: 2024-01-17 | C3: C041 | D3: Deepak Mehta | E3: P040 | F3: Soft Toy | G3: E04 | H3: Fatima Sheikh | I3: West | J3: 1212.79 | K3: 4 | L3: 0 | M3: 4851.16 | N3: 4851.16 | O3: 2024-01-19 | P3: Net Banking
A4: O0379 | B4: 2024-01-27 | C4: C051 | D4: Deepak Verma | E4: P019 | F4: Face Wash | G4: E09 | H4: Rajesh Iyer | I4: West | J4: 928.72 | K4: 2 | L4: 0 | M4: 1857.44 | N4: 1857.44 | O4: 2024-02-05 | P4: Net Banking
A5: O0377 | B5: 2024-11-11 | C5: C058 | D5: Neha Sharma | E5: P042 | F5: Action Figure | G5: E01 | H5: Karan Mehta | I5: West | J5: 4390.62 | K5: 8 | L5: 0 | M5: 35124.96 | N5: 35124.96 | O5: 2024-11-16 | P5: UPI
A6: O0376 | B6: 2025-02-02 | C6: C011 | D6: Aarav Patel | E6: P001 | F6: Wireless Mouse | G6: E03 | H6: Rohit Sinha | I6: West | J6: 2352.63 | K6: 6 | L6: 0 | M6: 14115.78 | N6: 14115.78 | O6: 2025-02-04 | P6: Credit Card
A7: O0370 | B7: 2024-05-23 | C7: C020 | D7: Priya Sharma | E7: P016 | F7: LED Lamp | G7: E01 | H7: Karan Mehta | I7: West | J7: 3772.12 | K7: 2 | L7: 0.1 | M7: 7544.24 | N7: 6789.816 | O7: 2024-05-29 | P7: Credit Card
A8: O0367 | B8: 2024-02-03 | C8: C016 | D8: Sakshi Joshi | E8: P021 | F8: Lipstick | G8: E04 | H8: Fatima Sheikh | I8: West | J8: 1513.99 | K8: 3 | L8: 0.2 | M8: 4541.97 | N8: 3633.576 | O8: 2024-02-09 | P8: UPI
A9: O0362 | B9: 2024-09-06 | C9: C055 | D9: Meera Verma | E9: P045 | F9: Green Tea Pack | G9: E02 | H9: Priya Nair | I9: West | J9: 3576.75 | K9: 4 | L9: 0 | M9: 14307 | N9: 14307 | O9: 2024-09-08 | P9: Credit Card
A10: O0359 | B10: 2025-05-29 | C10: C034 | D10: Sakshi Verma | E10: P015 | F10: Ceramic Mug Set | G10: E09 | H10: Rajesh Iyer | I10: West | J10: 2849.53 | K10: 7 | L10: 0.2 | M10: 19946.71 | N10: 15957.368 | O10: 2025-06-01 | P10: Credit Card
A11: O0353 | B11: 2025-05-15 | C11: C020 | D11: Priya Sharma | E11: P003 | F11: USB-C Charger | G11: E04 | H11: Fatima Sheikh | I11: West | J11: 3550.89 | K11: 3 | L11: 0.1 | M11: 10652.67 | N11: 9587.403 | O11: 2025-05-16 | P11: Credit Card
A12: O0341 | B12: 2024-07-14 | C12: C008 | D12: Karan Verma | E12: P002 | F12: Bluetooth Speaker | G12: E01 | H12: Karan Mehta | I12: West | J12: 991.59 | K12: 1 | L12: 0 | M12: 991.59 | N12: 991.59 | O12: 2024-07-21 | P12: Credit Card
A13: O0012 | B13: 2025-05-21 | C13: C017 | D13: Amit Shah | E13: P033 | F13: Cookbook | G13: E04 | H13: Fatima Sheikh | I13: West | J13: 2316.2 | K13: 7 | L13: 0 | M13: 16213.4 | N13: 16213.4 | O13: 2025-05-24 | P13: Credit Card
... A63: O0203 | B63: 2025-06-09 | C63: C059 | D63: Sakshi Gupta | E63: P019 | F63: Face Wash | G63: E02 | H63: Priya Nair | I63: West | J63: 928.72 | K63: 3 | L63: 0.2 | M63: 2786.16 | N63: 2228.928 | O63: 2025-06-16 | P63: UPI
A64: O0201 | B64: 2024-02-23 | C64: C055 | D64: Meera Verma | E64: P016 | F64: LED Lamp | G64: E02 | H64: Priya Nair | I64: West | J64: 3772.12 | K64: 0 | L64: 0.2 | M64: 0 | N64: 0 | O64: 2024-02-29 | P64: Net Banking | Q64: Missing Quantity
A65: O0064 | B65: 2025-03-15 | C65: C024 | D65: Anjali Joshi | E65: P013 | F65: Non-stick Pan | G65: E09 | H65: Rajesh Iyer | I65: West | J65: 3981.64 | K65: 5 | L65: 0.1 | M65: 19908.2 | N65: 17917.38 | O65: 2025-03-25 | P65: Net Banking
A66: O0194 | B66: 2024-04-13 | C66: C017 | D66: Amit Shah | E66: P032 | F66: Self-Help Book | G66: E02 | H66: Priya Nair | I66: West | J66: 605.26 | K66: 9 | L66: 0.2 | M66: 5447.34 | N66: 4357.872 | O66: 2024-04-22 | P66: Cash on Delivery
A67: O0066 | B67: 2024-06-09 | C67: C045 | D67: Aditya Joshi | E67: P030 | F67: Water Bottle | G67: E09 | H67: Rajesh Iyer | I67: West | J67: 2877.99 | K67: 4 | L67: 0 | M67: 11511.96 | N67: 11511.96 | O67: 2024-06-18 | P67: UPI
A68: O0193 | B68: 2024-07-15 | C68: C026 | D68: Sneha Joshi | E68: P029 | F68: Skipping Rope | G68: E09 | H68: Rajesh Iyer | I68: West | J68: 1187.29 | K68: 4 | L68: 0 | M68: 4749.16 | N68: 4749.16 | O68: 2024-07-18 | P68: Cash on Delivery
A69: O0186 | B69: 2025-01-31 | C69: C051 | D69: Deepak Verma | E69: P031 | F69: Novel - Fiction | G69: E03 | H69: Rohit Sinha | I69: West | J69: 2128.4 | K69: 7 | L69: 0.2 | M69: 14898.8 | N69: 11919.04 | O69: 2025-02-06 | P69: Cash on Delivery
A70: O0183 | B70: 2025-04-06 | C70: C030 | D70: Aditya Mehta | E70: P023 | F70: Sunscreen | G70: E04 | H70: Fatima Sheikh | I70: West | J70: 2405.98 | K70: 2 | L70: 0.2 | M70: 4811.96 | N70: 3849.568 | O70: 2025-04-12 | P70: Net Banking
A71: O0181 | B71: 2025-06-03 | C71: C018 | D71: Meera Verma | E71: P040 | F71: Soft Toy | G71: E03 | H71: Rohit Sinha | I71: West | J71: 1212.79 | K71: 7 | L71: 0.05 | M71: 8489.53 | N71: 8065.0535 | O71: 2025-06-13 | P71: Debit Card
A72: O0180 | B72: 2024-02-28 | C72: C001 | D72: Yash Mehta | E72: P032 | F72: Self-Help Book | G72: E03 | H72: Rohit Sinha | I72: West | J72: 605.26 | K72: 6 | L72: 0.2 | M72: 3631.56 | N72: 2905.248 | O72: 2024-03-04 | P72: Credit Card
A73: O0178 | B73: 2025-03-28 | C73: C060 | D73: Anjali Patel | E73: P017 | F73: Storage Box | G73: E04 | H73: Fatima Sheikh | I73: West | J73: 2612.71 | K73: 5 | L73: 0.2 | M73: 13063.55 | N73: 10450.84 | O73: 2025-04-02 | P73: Cash on Delivery
A74: O0073 | B74: 2025-05-27 | C74: C056 | D74: Mehul Mehta | E74: P033 | F74: Cookbook | G74: E01 | H74: Karan Mehta | I74: West | J74: 2316.2 | K74: 9 | L74: 0.05 | M74: 20845.8 | N74: 19803.51 | O74: 2025-06-04 | P74: Net Banking
A75: O0177 | B75: 2024-11-26 | C75: C025 | D75: Aarav Joshi | E75: P048 | F75: Spice Combo | G75: E02 | H75: Priya Nair | I75: West | J75: 2041.83 | K75: 6 | L75: 0 | M75: 12250.98 | N75: 12250.98 | O75: 2024-12-04 | P75: Debit Card
A76: O0075 | B76: 2024-04-03 | C76: C003 | D76: Kavya Shah | E76: P029 | F76: Skipping Rope | G76: E09 | H76: Rajesh Iyer | I76: West | J76: 1187.29 | K76: 4 | L76: 0.15 | M76: 4749.16 | N76: 4036.786 | O76: 2024-04-13 | P76: Cash on Delivery
... A104: O0111 | B104: 2024-01-23 | C104: C038 | D104: Deepak Patel | E104: P034 | F104: Notebook Set | G104: E01 | H104: Karan Mehta | I104: West | J104: 2036.67 | K104: 7 | L104: 0 | M104: 14256.69 | N104: 14256.69 | O104: 2024-01-24 | P104: Net Banking

Sheet Products
A1: ProductID | B1: ProductName | C1: Category | D1: CostPrice | E1: SellingPrice | F1: StockQty
A2: P001 | B2: Wireless Mouse | C2: Electronics | D2: 1936.31 | E2: 2352.63 | F2: 140
A3: P002 | B3: Bluetooth Speaker | C3: Electronics | D3: 772.43 | E3: 991.59 | F3: 52
A4: P003 | B4: USB-C Charger | C4: Electronics | D4: 2046.26 | E4: 3550.89 | F4: 44
A5: P004 | B5: Laptop Stand | C5: Electronics | D5: 1791.95 | E5: 2184.51 | F5: 47
A6: P005 | B6: Earbuds | C6: Electronics | D6: 694.98 | E6: 1044.7 | F6: 13
A7: P006 | B7: Power Bank | C7: Electronics | D7: 1705.67 | E7: 2779.58 | F7: 359
A8: P007 | B8: Cotton T-Shirt | C8: Clothing | D8: 1657.58 | E8: 2208.33 | F8: 301
A9: P008 | B9: Denim Jeans | C9: Clothing | D9: 870.66 | E9: 1498.91 | F9: 388
A10: P009 | B10: Hoodie | C10: Clothing | D10: 2427.17 | E10: 3929.31 | F10: 174
A11: P010 | B11: Formal Shirt | C11: Clothing | D11: 869.72 | E11: 1156.02 | F11: 390
A12: P011 | B12: Sports Jacket | C12: Clothing | D12: 1042.95 | E12: 1309.58 | F12: 49
A13: P012 | B13: Winter Scarf | C13: Clothing | D13: 1108.99 | E13: 1559.65 | F13: 135
... A49: P048 | B49: Spice Combo | C49: Grocery | D49: 1547.61 | E49: 2041.83 | F49: 191

Sheet Customers
A1: CustomerID | B1: CustomerName | C1: Email | D1: City | E1: JoinDate
A2: C001 | B2: Yash Mehta | C2: yash.mehta1@example.com | D2: Mumbai | E2: 2024-09-05
A3: C002 | B3: Pooja Shah | C3: pooja.shah2@example.com | D3: Porbandar | E3: 2024-01-07
A4: C003 | B4: Kavya Shah | C4: kavya.shah3@example.com | D4: Jaipur | E4: 2025-06-18
A5: C004 | B5: Aditya Patel | C5: aditya.patel4@example.com | D5: Surat | E5: 2025-04-15
A6: C005 | B6: Yash Kumar | C6: yash.kumar5@example.com | D6: Delhi | E6: 2023-05-12
A7: C006 | B7: Riya Mehta | C7: riya.mehta6@example.com | D7: Jaipur | E7: 2024-06-24
A8: C007 | B8: Divya Gupta | C8: divya.gupta7@example.com | D8: Porbandar | E8: 2024-12-31
A9: C008 | B9: Karan Verma | C9: karan.verma8@example.com | D9: Delhi | E9: 2024-06-13
A10: C009 | B10: Ananya Gupta | C10: ananya.gupta9@example.com | D10: Mumbai | E10: 2023-03-07
A11: C010 | B11: Aarav Singh | C11: aarav.singh10@example.com | D11: Rajkot | E11: 2024-08-25
A12: C011 | B12: Aarav Patel | C12: aarav.patel11@example.com | D12: Surat | E12: 2023-08-23
... A26: C025 | B26: Aarav Joshi | C26: aarav.joshi25@example.com | D26: Delhi | E26: 2025-03-13
A27: C026 | B27: Sneha Joshi | C27: sneha.joshi26@example.com | E27: 2023-06-08
A28: C027 | B28: Sneha Gupta | C28: sneha.gupta27@example.com | D28: Bengaluru | E28: 2024-08-16
A29: C028 | B29: Vivaan Verma | C29: vivaan.verma28@example.com | D29: Jaipur | E29: 2023-02-21
A30: C029 | B30: Pooja Kumar | C30: pooja.kumar29@example.com | D30: Bengaluru | E30: 2023-02-28
A31: C030 | B31: Aditya Mehta | C31: aditya.mehta30@example.com | D31: Surat | E31: 2024-09-01
A32: C031 | B32: Sakshi Gupta | C32: sakshi.gupta31@example.com | D32: Jaipur | E32: 2023-05-03
A33: C032 | B33: Kavya Singh | C33: kavya.singh32@example.com | D33: Surat | E33: 2024-09-26
A34: C033 | B34: Divya Singh | C34: divya.singh33@example.com | D34: Rajkot | E34: 2023-09-25
A35: C034 | B35: Sakshi Verma | C35: sakshi.verma34@example.com | D35: Pune | E35: 2023-09-29
A36: C035 | B36: Isha Sharma | C36: isha.sharma35@example.com | D36: Surat | E36: 2023-11-20
A37: C036 | B37: Aarav Desai | C37: aarav.desai36@example.com | D37: Bengaluru | E37: 2023-03-17
A38: C037 | B38: Rohan Kumar | C38: rohan.kumar37@example.com | D38: Mumbai | E38: 2023-05-16
A39: C038 | B39: Deepak Patel | C39: deepak.patel38@example.com | D39: Porbandar | E39: 2024-01-14
... A44: C043 | B44: Tanya Gupta | C44: tanya.gupta43@example.com | D44: Porbandar | E44: 2023-07-28
A45: C044 | B45: Sanjay Desai | C45: sanjay.desai44@example.com | E45: 2025-05-16
A46: C045 | B46: Aditya Joshi | C46: aditya.joshi45@example.com | D46: Ahmedabad | E46: 2023-02-15
A47: C046 | B47: Rahul Mehta | C47: rahul.mehta46@example.com | D47: Delhi | E47: 2023-06-15
A48: C047 | B48: Riya Joshi | C48: riya.joshi47@example.com | D48: Surat | E48: 2023-04-25
A49: C048 | B49: Deepak Mehta | C49: deepak.mehta48@example.com | D49: Mumbai | E49: 2025-05-04
A50: C049 | B50: Arjun Kumar | C50: arjun.kumar49@example.com | D50: Vadodara | E50: 2024-03-16
A51: C050 | B51: Vivaan Sharma | C51: vivaan.sharma50@example.com | D51: Ahmedabad | E51: 2025-03-26
A52: C051 | B52: Deepak Verma | C52: deepak.verma51@example.com | D52: Rajkot | E52: 2024-11-29
A53: C052 | B53: Sakshi Patel | C53: sakshi.patel52@example.com | D53: Bengaluru | E53: 2025-03-09
A54: C053 | B54: Deepak Joshi | C54: deepak.joshi53@example.com | D54: Vadodara | E54: 2023-08-31
A55: C054 | B55: Simran Mehta | C55: simran.mehta54@example.com | E55: 2023-01-26
A56: C055 | B56: Meera Verma | C56: meera.verma55@example.com | D56: Rajkot | E56: 2025-04-01
A57: C056 | B57: Mehul Mehta | C57: mehul.mehta56@example.com | D57: Ahmedabad | E57: 2024-01-27
A58: C057 | B58: Anjali Desai | C58: anjali.desai57@example.com | D58: Delhi | E58: 2023-07-24
A59: C058 | B59: Neha Sharma | C59: neha.sharma58@example.com | D59: Ahmedabad | E59: 2023-08-17
A60: C059 | B60: Sakshi Gupta | C60: sakshi.gupta59@example.com | D60: Porbandar | E60: 2023-12-03
A61: C060 | B61: Anjali Patel | C61: anjali.patel60@example.com | D61: Bengaluru | E61: 2023-12-26

Sheet Sheet1
A1: OrderID | B1: OrderDate | C1: CustomerID | D1: Customer Name | E1: ProductID | F1: Product Name | G1: EmployeeID | H1: Employee Name | I1: Category | J1: Region | K1: Selling Price | L1: Quantity | M1: Discount | N1: Total amount | O1: Revenue | P1: ShipDate | Q1: PaymentMethod | R1: Data Issue
A2: O0001 | B2: 45738 | C2: C042 | D2: Meera Kumar | E2: P028 | F2: Football | G2: E04 | H2: Fatima Sheikh | I2: Sports | J2: North | K2: 3493.54 | L2: 1 | M2: 0.1 | N2: 3493.54 | O2: 3144.186 | P2: 2025-03-31 | Q2: Cash on Delivery
A3: O0388 | B3: 45431 | C3: C057 | D3: Anjali Desai | E3: P028 | F3: USB-C Charger | G3: E04 | H3: Fatima Sheikh | I3: Sports | J3: North | K3: 3493.54 | L3: 5 | M3: 0 | N3: 17467.7 | O3: 17467.7 | P3: 2024-05-29 | Q3: Debit Card
A4: O0347 | B4: 45392 | C4: C036 | D4: Aarav Desai | E4: P028 | F4: Self-Help Book | G4: E01 | H4: Karan Mehta | I4: Sports | J4: North | K4: 3493.54 | L4: 8 | M4: 0.2 | N4: 27948.32 | O4: 22358.656 | P4: 2024-04-16 | Q4: Cash on Delivery
A5: O0330 | B5: 45326 | C5: C015 | D5: Simran Joshi | E5: P027 | F5: Soft Toy | G5: E01 | H5: Karan Mehta | I5: Sports | J5: North | K5: 3128.51 | L5: 8 | M5: 0.1 | N5: 25028.08 | O5: 22525.272 | P5: 2024-02-05 | Q5: Credit Card
A6: O0311 | B6: 45594 | C6: C008 | D6: Karan Verma | E6: P025 | F6: Sunscreen | G6: E01 | H6: Karan Mehta | I6: Sports | J6: North | K6: 4703.04 | L6: 6 | M6: 0.1 | N6: 28218.24 | O6: 25396.416 | P6: 2024-11-02 | Q6: UPI
A7: O0287 | B7: 45544 | C7: C019 | D7: Rohan Kumar | E7: P027 | F7: Soft Toy | G7: E09 | H7: Rajesh Iyer | I7: Sports | J7: North | K7: 3128.51 | L7: 5 | M7: 0.1 | N7: 15642.55 | O7: 14078.295 | P7: 2024-09-14 | Q7: Cash on Delivery
A8: O0189 | B8: 45436 | C8: C028 | D8: Vivaan Verma | E8: P028 | F8: Hoodie | G8: E02 | H8: Priya Nair | I8: Sports | J8: North | K8: 3493.54 | L8: 6 | M8: 0 | N8: 20961.24 | O8: 20961.24 | P8: 2024-05-31 | Q8: Net Banking
A9: O0133 | B9: 45294 | C9: C050 | D9: Vivaan Sharma | E9: P025 | F9: Power Bank | G9: E09 | H9: Rajesh Iyer | I9: Sports | J9: North | K9: 4703.04 | L9: 5 | M9: 0.2 | N9: 23515.2 | O9: 18812.16 | P9: 2024-01-06 | Q9: Net Banking
A10: O0105 | B10: 45471 | C10: C057 | D10: Anjali Desai | E10: P026 | F10: Dumbbell Set | G10: E02 | H10: Priya Nair | I10: Sports | J10: North | K10: 973.21 | L10: 2 | M10: 0.1 | N10: 1946.42 | O10: 1751.778 | P10: 2024-07-05 | Q10: Debit Card
A11: O0010 | B11: 45495 | C11: C013 | D11: Kavya Sharma | E11: P028 | F11: Football | G11: E04 | H11: Fatima Sheikh | I11: Sports | J11: North | K11: 3493.54 | L11: 3 | M11: 0 | N11: 10480.62 | O11: 10480.62 | P11: 2024-07-23 | Q11: Debit Card
A12: O0048 | B12: 45539 | C12: C011 | D12: Aarav Patel | E12: P029 | F12: Skipping Rope | G12: E09 | H12: Rajesh Iyer | I12: Sports | J12: North | K12: 1187.29 | L12: 7 | M12: 0.05 | N12: 8311.03 | O12: 7895.4785 | P12: 2024-09-13 | Q12: Debit Card
A13: O0041 | B13: 45735 | C13: C005 | D13: Yash Kumar | E13: P027 | F13: Cricket Bat | G13: E03 | H13: Rohit Sinha | I13: Sports | J13: North | K13: 3128.51 | L13: 6 | M13: 0.15 | N13: 18771.06 | O13: 15955.401 | P13: 2025-03-27 | Q13: Debit Card

Sheet Sheet4
A1: OrderID | B1: OrderDate | C1: CustomerID | D1: Customer Name | E1: ProductID | F1: Product Name | G1: EmployeeID | H1: Employee Name | I1: Category | J1: Region | K1: Selling Price | L1: Quantity | M1: Discount | N1: Total amount | O1: Revenue | P1: ShipDate | Q1: PaymentMethod | R1: Data Issue
A2: O0001 | B2: 45738 | C2: C042 | D2: Meera Kumar | E2: P028 | F2: Football | G2: E04 | H2: Fatima Sheikh | I2: Sports | J2: North | K2: 3493.54 | L2: 1 | M2: 0.1 | N2: 3493.54 | O2: 3144.186 | P2: 2025-03-31 | Q2: Cash on Delivery
A3: O0002 | B3: 45733 | C3: C029 | D3: Pooja Kumar | E3: P016 | F3: LED Lamp | G3: E01 | H3: Karan Mehta | I3: Home & Kitchen | J3: South | K3: 3772.12 | L3: 2 | M3: 0.15 | N3: 7544.24 | O3: 6412.604 | P3: 2025-03-23 | Q3: Credit Card
A4: O0003 | B4: 45599 | C4: C013 | D4: Kavya Sharma | E4: P014 | F4: Blender | G4: E04 | H4: Fatima Sheikh | I4: Home & Kitchen | J4: South | K4: 733.33 | L4: 9 | M4: 0 | N4: 6599.97 | O4: 6599.97 | P4: 2024-11-10 | Q4: Debit Card
A5: O0004 | B5: 45594 | C5: C044 | D5: Sanjay Desai | E5: P044 | F5: Cooking Oil 1L | G5: E03 | H5: Rohit Sinha | I5: Grocery | J5: East | K5: 620.89 | L5: 9 | M5: 0 | N5: 5588.01 | O5: 5588.01 | P5: 2024-11-02 | Q5: Debit Card
A6: O0005 | B6: 45470 | C6: C021 | D6: Amit Kumar | E6: P041 | F6: Board Game | G6: E03 | H6: Rohit Sinha | I6: Toys | J6: East | K6: 136.91 | L6: 10 | M6: 0.1 | N6: 1369.1 | O6: 1232.19 | P6: 2024-07-02 | Q6: Net Banking
A7: O0006 | B7: 45292 | C7: C021 | D7: Amit Kumar | E7: P026 | F7: Dumbbell Set | G7: E09 | H7: Rajesh Iyer | I7: Sports | J7: East | K7: 973.21 | L7: 5 | M7: 0 | N7: 4866.05 | O7: 4866.05 | P7: 2024-01-05 | Q7: Net Banking
A8: O0007 | B8: 45621 | C8: C040 | D8: Aarav Kumar | E8: P048 | F8: Spice Combo | G8: E04 | H8: Fatima Sheikh | I8: Grocery | J8: North | K8: 2041.83 | L8: 8 | M8: 0.05 | N8: 16334.64 | O8: 15517.908 | P8: 2024-12-03 | Q8: Net Banking
A9: O0008 | B9: 45776 | C9: C041 | D9: Deepak Mehta | E9: P009 | F9: Hoodie | G9: E03 | H9: Rohit Sinha | I9: Clothing | J9: South | K9: 3929.31 | L9: 3 | M9: 0.15 | N9: 11787.93 | O9: 10019.74 | P9: 2025-05-01 | Q9: Net Banking
A10: O0009 | B10: 45635 | C10: C032 | D10: Kavya Singh | E10: P016 | F10: LED Lamp | G10: E04 | H10: Fatima Sheikh | I10: Home & Kitchen | J10: South | K10: 3772.12 | L10: 2 | M10: 0.2 | N10: 7544.24 | O10: 6035.392 | P10: 2024-12-13 | Q10: UPI
A11: O0010 | B11: 45495 | C11: C013 | D11: Kavya Sharma | E11: P028 | F11: Football | G11: E04 | H11: Fatima Sheikh | I11: Sports | J11: North | K11: 3493.54 | L11: 3 | M11: 0 | N11: 10480.62 | O11: 10480.62 | P11: 2024-07-23 | Q11: Debit Card
A12: O0011 | B12: 45366 | C12: C008 | D12: Karan Verma | E12: P038 | F12: Remote Car | G12: E04 | H12: Fatima Sheikh | I12: Toys | J12: North | K12: 3205.14 | L12: 8 | M12: 0.05 | N12: 25641.12 | O12: 24359.064 | P12: 2024-03-25 | Q12: Debit Card
A13: O0012 | B13: 45798 | C13: C017 | D13: Amit Shah | E13: P033 | F13: Cookbook | G13: E04 | H13: Fatima Sheikh | I13: Books | J13: West | K13: 2316.2 | L13: 7 | M13: 0 | N13: 16213.4 | O13: 16213.4 | P13: 2025-05-24 | Q13: Credit Card
... A193: O0191 | B193: 45831 | C193: C058 | D193: Neha Sharma | E193: P001 | F193: Skipping Rope | G193: E09 | H193: Rajesh Iyer | I193: Electronics | J193: South | K193: 2352.63 | L193: 2 | M193: 0.15 | N193: 4705.26 | O193: 3999.471 | P193: 2025-06-30 | Q193: Credit Card
A194: O0192 | B194: 45663 | C194: C019 | D194: Rohan Kumar | E194: P013 | F194: Wireless Mouse | G194: E01 | H194: Karan Mehta | I194: Home & Kitchen | J194: South | K194: 3981.64 | L194: 0 | M194: 0 | N194: 0 | O194: 0 | P194: 2025-01-10 | Q194: Debit Card | R194: Missing Quantity
A195: O0193 | B195: 45488 | C195: C026 | D195: Sneha Joshi | E195: P029 | F195: Non-stick Pan | G195: E09 | H195: Rajesh Iyer | I195: Sports | J195: West | K195: 1187.29 | L195: 4 | M195: 0 | N195: 4749.16 | O195: 4749.16 | P195: 2024-07-18 | Q195: Cash on Delivery
A196: O0194 | B196: 45395 | C196: C017 | D196: Amit Shah | E196: P032 | F196: Skipping Rope | G196: E02 | H196: Priya Nair | I196: Books | J196: West | K196: 605.26 | L196: 9 | M196: 0.2 | N196: 5447.34 | O196: 4357.872 | P196: 2024-04-22 | Q196: Cash on Delivery
A197: O0195 | B197: 45426 | C197: C039 | D197: Priya Desai | E197: P001 | F197: Self-Help Book | G197: E03 | H197: Rohit Sinha | I197: Electronics | J197: North | K197: 2352.63 | L197: 10 | M197: 0.05 | N197: 23526.3 | O197: 22349.985 | P197: 2024-05-17 | Q197: UPI
A198: O0196 | B198: 45461 | C198: C010 | D198: Aarav Singh | E198: P014 | F198: Wireless Mouse | G198: E03 | H198: Rohit Sinha | I198: Home & Kitchen | J198: South | K198: 733.33 | L198: 8 | M198: 0 | N198: 5866.64 | O198: 5866.64 | P198: 2024-06-25 | Q198: UPI
A199: O0197 | B199: 45746 | C199: C003 | D199: Kavya Shah | E199: P045 | F199: Blender | G199: E01 | H199: Karan Mehta | I199: Grocery | J199: North | K199: 3576.75 | L199: 10 | M199: 0 | N199: 35767.5 | O199: 35767.5 | P199: 2025-04-07 | Q199: Net Banking
A200: O0198 | B200: 45536 | C200: C060 | D200: Anjali Patel | E200: P035 | F200: Green Tea Pack | G200: E04 | H200: Fatima Sheikh | I200: Books | J200: North | K200: 1253.57 | L200: 5 | M200: 0.2 | N200: 6267.85 | O200: 5014.28 | P200: 2024-09-09 | Q200: Cash on Delivery
A201: O0199 | B201: 45743 | C201: C047 | D201: Riya Joshi | E201: P038 | F201: Comic Book | G201: E01 | H201: Karan Mehta | I201: Toys | J201: East | K201: 3205.14 | L201: 8 | M201: 0.2 | N201: 25641.12 | O201: 20512.896 | P201: 2025-04-01 | Q201: Net Banking
A202: O0200 | B202: 45832 | C202: C020 | D202: Priya Sharma | E202: P011 | F202: Remote Car | G202: E04 | H202: Fatima Sheikh | I202: Clothing | J202: North | K202: 1309.58 | L202: 7 | M202: 0 | N202: 9167.06 | O202: 9167.06 | P202: 2025-06-28 | Q202: Cash on Delivery
A203: O0201 | B203: 45345 | C203: C055 | D203: Meera Verma | E203: P016 | F203: Sports Jacket | G203: E02 | H203: Priya Nair | I203: Home & Kitchen | J203: West | K203: 3772.12 | L203: 0 | M203: 0.2 | N203: 0 | O203: 0 | P203: 2024-02-29 | Q203: Net Banking | R203: Missing Quantity
A204: O0202 | B204: 45419 | C204: C059 | D204: Sakshi Gupta | E204: P027 | F204: LED Lamp | G204: E02 | H204: Priya Nair | I204: Sports | J204: South | K204: 3128.51 | L204: 5 | M204: 0 | N204: 15642.55 | O204: 15642.55 | P204: 2024-05-10 | Q204: Debit Card
A205: O0203 | B205: 45817 | C205: C059 | D205: Sakshi Gupta | E205: P019 | F205: Cricket Bat | G205: E02 | H205: Priya Nair | I205: Beauty | J205: West | K205: 928.72 | L205: 3 | M205: 0.2 | N205: 2786.16 | O205: 2228.928 | P205: 2025-06-16 | Q205: UPI
A206: O0204 | B206: 45753 | C206: C012 | D206: Deepak Shah | E206: P002 | F206: Face Wash | G206: E02 | H206: Priya Nair | I206: Electronics | J206: West | K206: 991.59 | L206: 6 | M206: 0 | N206: 5949.54 | O206: 5949.54 | P206: 2025-04-13 | Q206: Debit Card
A207: O0205 | B207: 45806 | C207: C024 | D207: Anjali Joshi | E207: P037 | F207: Bluetooth Speaker | G207: E03 | H207: Rohit Sinha | I207: Toys | J207: West | K207: 588.75 | L207: 6 | M207: 0 | N207: 3532.5 | O207: 3532.5 | P207: 2025-06-05 | Q207: Cash on Delivery
A208: O0206 | B208: 45521 | C208: C024 | D208: Anjali Joshi | E208: P044 | F208: Building Blocks | G208: E03 | H208: Rohit Sinha | I208: Grocery | J208: South | K208: 620.89 | L208: 1 | M208: 0 | N208: 620.89 | O208: 620.89 | P208: 2024-08-19 | Q208: UPI
A209: O0207 | B209: 45432 | C209: C017 | D209: Amit Shah | E209: P020 | F209: Cooking Oil 1L | G209: E03 | H209: Rohit Sinha | I209: Beauty | J209: North | K209: 2359.5 | L209: 1 | M209: 0 | N209: 2359.5 | O209: 2359.5 | P209: 2024-05-28 | Q209: Debit Card
A210: O0208 | B210: 45751 | C210: C053 | D210: Deepak Joshi | E210: P020 | F210: Moisturizer | G210: E01 | H210: Karan Mehta | I210: Beauty | J210: West | K210: 2359.5 | L210: 10 | M210: 0 | N210: 23595 | O210: 23595 | P210: 2025-04-06 | Q210: Cash on Delivery
A211: O0209 | B211: 45512 | C211: C013 | D211: Kavya Sharma | E211: P039 | F211: Moisturizer | G211: E02 | H211: Priya Nair | I211: Toys | J211: East | K211: 2113.67 | L211: 3 | M211: 0.1 | N211: 6341.01 | O211: 5706.909 | P211: 2024-08-18 | Q211: Credit Card
A212: O0210 | B212: 45587 | C212: C023 | D212: Priya Joshi | E212: P044 | F212: Puzzle Set | G212: E02 | H212: Priya Nair | I212: Grocery | J212: West | K212: 620.89 | L212: 4 | M212: 0 | N212: 2483.56 | O212: 2483.56 | P212: 2024-10-24 | Q212: UPI
A213: O0211 | B213: 45721 | C213: C046 | D213: Rahul Mehta | E213: P039 | F213: Cooking Oil 1L | G213: E01 | H213: Karan Mehta | I213: Toys | J213: West | K213: 2113.67 | L213: 10 | M213: 0.05 | N213: 21136.7 | O213: 20079.865 | P213: 2025-03-07 | Q213: Debit Card
A214: O0212 | B214: 45308 | C214: C045 | D214: Aditya Joshi | E214: P041 | F214: Puzzle Set | G214: E01 | H214: Karan Mehta | I214: Toys | J214: North | K214: 136.91 | L214: 9 | M214: 0.1 | N214: 1232.19 | O214: 1108.971 | P214: 2024-01-21 | Q214: Cash on Delivery
A215: O0213 | B215: 45731 | C215: C024 | D215: Anjali Joshi | E215: P012 | F215: Board Game | G215: E09 | H215: Rajesh Iyer | I215: Clothing | J215: North | K215: 1559.65 | L215: 1 | M215: 0.1 | N215: 1559.65 | O215: 1403.685 | P215: 2025-03-21 | Q215: Net Banking
... A239: O0237 | B239: 45803 | C239: C055 | D239: Meera Verma | E239: P022 | F239: Remote Car | G239: E02 | H239: Priya Nair | I239: Beauty | J239: West | K239: 3414.07 | L239: 9 | M239: 0.05 | N239: 30726.63 | O239: 29190.299 | P239: 2025-06-04 | Q239: Cash on Delivery
A240: O0238 | B240: 45558 | C240: C002 | D240: Pooja Shah | E240: P006 | F240: Hair Serum | G240: E01 | H240: Karan Mehta | I240: Electronics | J240: South | K240: 2779.58 | L240: 0 | M240: 0 | N240: 0 | O240: 0 | P240: 2024-10-03 | Q240: Debit Card | R240: Missing Quantity
A241: O0239 | B241: 45496 | C241: C023 | D241: Priya Joshi | E241: P013 | F241: Power Bank | G241: E02 | H241: Priya Nair | I241: Home & Kitchen | J241: East | K241: 3981.64 | L241: 2 | M241: 0 | N241: 7963.28 | O241: 7963.28 | P241: 2024-07-25 | Q241: UPI
A242: O0240 | B242: 45747 | C242: C022 | D242: Rajesh Shah | E242: P010 | F242: Non-stick Pan | G242: E01 | H242: Karan Mehta | I242: Clothing | J242: South | K242: 1156.02 | L242: 2 | M242: 0.2 | N242: 2312.04 | O242: 1849.632 | P242: 2025-04-06 | Q242: Credit Card
A243: O0241 | B243: 45589 | C243: C015 | D243: Simran Joshi | E243: P034 | F243: Formal Shirt | G243: E02 | H243: Priya Nair | I243: Books | J243: North | K243: 2036.67 | L243: 5 | M243: 0.2 | N243: 10183.35 | O243: 8146.68 | P243: 2024-10-27 | Q243: Cash on Delivery
A244: O0242 | B244: 45812 | C244: C041 | D244: Deepak Mehta | E244: P039 | F244: Notebook Set | G244: E02 | H244: Priya Nair | I244: Toys | J244: North | K244: 2113.67 | L244: 4 | M244: 0 | N244: 8454.68 | O244: 8454.68 | P244: 2025-06-08 | Q244: UPI
A245: O0243 | B245: 45797 | C245: C033 | D245: Divya Singh | E245: P004 | F245: Puzzle Set | G245: E02 | H245: Priya Nair | I245: Electronics | J245: South | K245: 2184.51 | L245: 1 | M245: 0 | N245: 2184.51 | O245: 2184.51 | P245: 2025-05-29 | Q245: Debit Card
A246: O0244 | B246: 45424 | C246: C040 | D246: Aarav Kumar | E246: P010 | F246: Laptop Stand | G246: E09 | H246: Rajesh Iyer | I246: Clothing | J246: South | K246: 1156.02 | L246: 10 | M246: 0 | N246: 11560.2 | O246: 11560.2 | P246: 2024-05-14 | Q246: Debit Card
A247: O0245 | B247: 45782 | C247: C056 | D247: Mehul Mehta | E247: P039 | F247: Formal Shirt | G247: E09 | H247: Rajesh Iyer | I247: Toys | J247: West | K247: 2113.67 | L247: 9 | M247: 0.05 | N247: 19023.03 | O247: 18071.878 | P247: 2025-05-12 | Q247: UPI
A248: O0246 | B248: 45616 | C248: C043 | D248: Tanya Gupta | E248: P039 | F248: Puzzle Set | G248: E02 | H248: Priya Nair | I248: Toys | J248: South | K248: 2113.67 | L248: 2 | M248: 0.05 | N248: 4227.34 | O248: 4015.973 | P248: 2024-11-28 | Q248: UPI
A249: O0247 | B249: 45478 | C249: C018 | D249: Meera Verma | E249: P039 | F249: Puzzle Set | G249: E02 | H249: Priya Nair | I249: Toys | J249: West | K249: 2113.67 | L249: 3 | M249: 0.05 | N249: 6341.01 | O249: 6023.9595 | P249: 2024-07-14 | Q249: Credit Card
A250: O0248 | B250: 45822 | C250: C051 | D250: Deepak Verma | E250: P044 | F250: Puzzle Set | G250: E02 | H250: Priya Nair | I250: Grocery | J250: North | K250: 620.89 | L250: 3 | M250: 0 | N250: 1862.67 | O250: 1862.67 | P250: 2025-06-17 | Q250: Cash on Delivery
A251: O0249 | B251: 45522 | C251: C031 | D251: Sakshi Gupta | E251: P040 | F251: Cooking Oil 1L | G251: E09 | H251: Rajesh Iyer | I251: Toys | J251: West | K251: 1212.79 | L251: 6 | M251: 0.1 | N251: 7276.74 | O251: 6549.066 | P251: 2024-08-23 | Q251: Cash on Delivery
A252: O0250 | B252: 45493 | C252: C033 | D252: Divya Singh | E252: P043 | F252: Soft Toy | G252: E09 | H252: Rajesh Iyer | I252: Grocery | J252: South | K252: 2458.91 | L252: 9 | M252: 0 | N252: 22130.19 | O252: 22130.19 | P252: 2024-07-23 | Q252: Net Banking
... A351: O0347 | B351: 45392 | C351: C036 | D351: Aarav Desai | E351: P028 | F351: Self-Help Book | G351: E01 | H351: Karan Mehta | I351: Sports | J351: North | K351: 3493.54 | L351: 8 | M351: 0.2 | N351: 27948.32 | O351: 22358.656 | P351: 2024-04-16 | Q351: Cash on Delivery
A352: O0348 | B352: 45612 | C352: C018 | D352: Meera Verma | E352: P008 | F352: Perfume | G352: E04 | H352: Fatima Sheikh | I352: Clothing | J352: North | K352: 1498.91 | L352: 0 | M352: 0 | N352: 0 | O352: 0 | P352: 2024-11-26 | Q352: UPI | R352: Missing Quantity
A353: O0349 | B353: 45308 | C353: C036 | D353: Aarav Desai | E353: P022 | F353: Hoodie | G353: E02 | H353: Priya Nair | I353: Beauty | J353: East | K353: 3414.07 | L353: 5 | M353: 0.1 | N353: 17070.35 | O353: 15363.315 | P353: 2024-01-27 | Q353: Cash on Delivery
A354: O0350 | B354: 45448 | C354: C041 | D354: Deepak Mehta | E354: P028 | F354: Football | G354: E04 | H354: Fatima Sheikh | I354: Sports | J354: East | K354: 3493.54 | L354: 4 | M354: 0 | N354: 13974.16 | O354: 13974.16 | P354: 2024-06-09 | Q354: Net Banking
A355: O0351 | B355: 45543 | C355: C051 | D355: Deepak Verma | E355: P025 | F355: Denim Jeans | G355: E02 | H355: Priya Nair | I355: Sports | J355: South | K355: 4703.04 | L355: 8 | M355: 0.1 | N355: 37624.32 | O355: 33861.888 | P355: 2024-09-14 | Q355: Debit Card
A356: O0352 | B356: 45794 | C356: C002 | D356: Pooja Shah | E356: P038 | F356: Hair Serum | G356: E09 | H356: Rajesh Iyer | I356: Toys | J356: North | K356: 3205.14 | L356: 8 | M356: 0 | N356: 25641.12 | O356: 25641.12 | P356: 2025-05-23 | Q356: UPI
A357: O0353 | B357: 45792 | C357: C020 | D357: Priya Sharma | E357: P003 | F357: Football | G357: E04 | H357: Fatima Sheikh | I357: Electronics | J357: West | K357: 3550.89 | L357: 3 | M357: 0.1 | N357: 10652.67 | O357: 9587.403 | P357: 2025-05-16 | Q357: Credit Card
A358: O0354 | B358: 45341 | C358: C015 | D358: Simran Joshi | E358: P033 | F358: Yoga Mat | G358: E01 | H358: Karan Mehta | I358: Books | J358: North | K358: 2316.2 | L358: 1 | M358: 0.05 | N358: 2316.2 | O358: 2200.39 | P358: 2024-02-22 | Q358: Credit Card
A359: O0355 | B359: 45446 | C359: C046 | D359: Rahul Mehta | E359: P035 | F359: Remote Car | G359: E09 | H359: Rajesh Iyer | I359: Books | J359: East | K359: 1253.57 | L359: 1 | M359: 0 | N359: 1253.57 | O359: 1253.57 | P359: 2024-06-12 | Q359: Cash on Delivery
A360: O0356 | B360: 45353 | C360: C023 | D360: Priya Joshi | E360: P013 | F360: USB-C Charger | G360: E02 | H360: Priya Nair | I360: Home & Kitchen | J360: East | K360: 3981.64 | L360: 10 | M360: 0.15 | N360: 39816.4 | O360: 33843.94 | P360: 2024-03-12 | Q360: Debit Card
A361: O0357 | B361: 45308 | C361: C054 | D361: Simran Mehta | E361: P041 | F361: Cookbook | G361: E02 | H361: Priya Nair | I361: Toys | J361: East | K361: 136.91 | L361: 1 | M361: 0.1 | N361: 136.91 | O361: 123.219 | P361: 2024-01-26 | Q361: Credit Card
A362: O0358 | B362: 45309 | C362: C039 | D362: Priya Desai | E362: P016 | F362: Comic Book | G362: E03 | H362: Rohit Sinha | I362: Home & Kitchen | J362: South | K362: 3772.12 | L362: 9 | M362: 0.15 | N362: 33949.08 | O362: 28856.718 | P362: 2024-01-23 | Q362: Credit Card
A363: O0359 | B363: 45806 | C363: C034 | D363: Sakshi Verma | E363: P015 | F363: Non-stick Pan | G363: E09 | H363: Rajesh Iyer | I363: Home & Kitchen | J363: West | K363: 2849.53 | L363: 7 | M363: 0.2 | N363: 19946.71 | O363: 15957.368 | P363: 2025-06-01 | Q363: Credit Card
A364: O0360 | B364: 45828 | C364: C053 | D364: Deepak Joshi | E364: P008 | F364: Board Game | G364: E03 | H364: Rohit Sinha | I364: Clothing | J364: South | K364: 1498.91 | L364: 3 | M364: 0 | N364: 4496.73 | O364: 4496.73 | P364: 2025-06-24 | Q364: Cash on Delivery
... A399: O0395 | B399: 45367 | C399: C033 | D399: Divya Singh | E399: P010 | F399: Football | G399: E04 | H399: Fatima Sheikh | I399: Clothing | J399: East | K399: 1156.02 | L399: 8 | M399: 0.1 | N399: 9248.16 | O399: 8323.344 | P399: 2024-03-24 | Q399: Net Banking
A400: O0396 | B400: 45810 | C400: C008 | D400: Karan Verma | E400: P020 | F400: Remote Car | G400: E04 | H400: Fatima Sheikh | I400: Beauty | J400: South | K400: 2359.5 | L400: 0 | M400: 0.1 | N400: 0 | O400: 0 | P400: 2025-06-03 | Q400: Net Banking | R400: Missing Quantity
A401: O0397 | B401: 45379 | C401: C029 | D401: Pooja Kumar | E401: P040 | F401: Laptop Stand | G401: E03 | H401: Rohit Sinha | I401: Toys | J401: South | K401: 1212.79 | L401: 2 | M401: 0.2 | N401: 2425.58 | O401: 1940.464 | P401: 2024-04-01 | Q401: UPI
A402: O0398 | B402: 45337 | C402: C049 | D402: Arjun Kumar | E402: P023 | F402: Formal Shirt | G402: E01 | H402: Karan Mehta | I402: Beauty | J402: South | K402: 2405.98 | L402: 10 | M402: 0.15 | N402: 24059.8 | O402: 20450.83 | P402: 2024-02-22 | Q402: Debit Card
A403: O0399 | B403: 45400 | C403: C027 | D403: Sneha Gupta | E403: P010 | F403: Moisturizer | G403: E01 | H403: Karan Mehta | I403: Clothing | J403: North | K403: 1156.02 | L403: 1 | M403: 0 | N403: 1156.02 | O403: 1156.02 | P403: 2024-04-23 | Q403: Net Banking
A404: O0404 | B404: 45400 | C404: C027 | D404: Sneha Gupta | E404: P010 | F404: Sunscreen | G404: E01 | H404: Karan Mehta | I404: Clothing | J404: North | K404: 1156.02 | L404: 1 | M404: 0 | N404: 1156.02 | O404: 1156.02 | P404: 2024-04-23 | Q404: Net Banking
A405: O0400 | B405: 45823 | C405: C018 | D405: Meera Verma | E405: P035 | F405: Soft Toy | G405: E04 | H405: Fatima Sheikh | I405: Books | J405: North | K405: 1253.57 | L405: 9 | M405: 0.1 | N405: 11282.13 | O405: 10153.917 | P405: 2025-06-25 | Q405: Debit Card

Sheet Sheet5
A1: OrderID | B1: OrderDate | C1: CustomerID | D1: Customer Name | E1: ProductID | F1: Product Name | G1: EmployeeID | H1: Employee Name | I1: Category | J1: Region | K1: Selling Price | L1: Quantity | M1: Discount | N1: Total amount | O1: Revenue | P1: ShipDate | Q1: PaymentMethod | R1: Data Issue
A2: O0001 | B2: 45738 | C2: C042 | D2: Meera Kumar | E2: P028 | F2: Football | G2: E04 | H2: Fatima Sheikh | I2: Sports | J2: North | K2: 3493.54 | L2: 1 | M2: 0.1 | N2: 3493.54 | O2: 3144.186 | P2: 2025-03-31 | Q2: Cash on Delivery
A3: O0002 | B3: 45733 | C3: C029 | D3: Pooja Kumar | E3: P016 | F3: LED Lamp | G3: E01 | H3: Karan Mehta | I3: Home & Kitchen | J3: South | K3: 3772.12 | L3: 2 | M3: 0.15 | N3: 7544.24 | O3: 6412.604 | P3: 2025-03-23 | Q3: Credit Card
A4: O0003 | B4: 45599 | C4: C013 | D4: Kavya Sharma | E4: P014 | F4: Blender | G4: E04 | H4: Fatima Sheikh | I4: Home & Kitchen | J4: South | K4: 733.33 | L4: 9 | M4: 0 | N4: 6599.97 | O4: 6599.97 | P4: 2024-11-10 | Q4: Debit Card
A5: O0004 | B5: 45594 | C5: C044 | D5: Sanjay Desai | E5: P044 | F5: Cooking Oil 1L | G5: E03 | H5: Rohit Sinha | I5: Grocery | J5: East | K5: 620.89 | L5: 9 | M5: 0 | N5: 5588.01 | O5: 5588.01 | P5: 2024-11-02 | Q5: Debit Card
A6: O0005 | B6: 45470 | C6: C021 | D6: Amit Kumar | E6: P041 | F6: Board Game | G6: E03 | H6: Rohit Sinha | I6: Toys | J6: East | K6: 136.91 | L6: 10 | M6: 0.1 | N6: 1369.1 | O6: 1232.19 | P6: 2024-07-02 | Q6: Net Banking
A7: O0006 | B7: 45292 | C7: C021 | D7: Amit Kumar | E7: P026 | F7: Dumbbell Set | G7: E09 | H7: Rajesh Iyer | I7: Sports | J7: East | K7: 973.21 | L7: 5 | M7: 0 | N7: 4866.05 | O7: 4866.05 | P7: 2024-01-05 | Q7: Net Banking
A8: O0007 | B8: 45621 | C8: C040 | D8: Aarav Kumar | E8: P048 | F8: Spice Combo | G8: E04 | H8: Fatima Sheikh | I8: Grocery | J8: North | K8: 2041.83 | L8: 8 | M8: 0.05 | N8: 16334.64 | O8: 15517.908 | P8: 2024-12-03 | Q8: Net Banking
A9: O0008 | B9: 45776 | C9: C041 | D9: Deepak Mehta | E9: P009 | F9: Hoodie | G9: E03 | H9: Rohit Sinha | I9: Clothing | J9: South | K9: 3929.31 | L9: 3 | M9: 0.15 | N9: 11787.93 | O9: 10019.74 | P9: 2025-05-01 | Q9: Net Banking
A10: O0009 | B10: 45635 | C10: C032 | D10: Kavya Singh | E10: P016 | F10: LED Lamp | G10: E04 | H10: Fatima Sheikh | I10: Home & Kitchen | J10: South | K10: 3772.12 | L10: 2 | M10: 0.2 | N10: 7544.24 | O10: 6035.392 | P10: 2024-12-13 | Q10: UPI
A11: O0010 | B11: 45495 | C11: C013 | D11: Kavya Sharma | E11: P028 | F11: Football | G11: E04 | H11: Fatima Sheikh | I11: Sports | J11: North | K11: 3493.54 | L11: 3 | M11: 0 | N11: 10480.62 | O11: 10480.62 | P11: 2024-07-23 | Q11: Debit Card
A12: O0011 | B12: 45366 | C12: C008 | D12: Karan Verma | E12: P038 | F12: Remote Car | G12: E04 | H12: Fatima Sheikh | I12: Toys | J12: North | K12: 3205.14 | L12: 8 | M12: 0.05 | N12: 25641.12 | O12: 24359.064 | P12: 2024-03-25 | Q12: Debit Card
A13: O0012 | B13: 45798 | C13: C017 | D13: Amit Shah | E13: P033 | F13: Cookbook | G13: E04 | H13: Fatima Sheikh | I13: Books | J13: West | K13: 2316.2 | L13: 7 | M13: 0 | N13: 16213.4 | O13: 16213.4 | P13: 2025-05-24 | Q13: Credit Card
... A193: O0191 | B193: 45831 | C193: C058 | D193: Neha Sharma | E193: P001 | F193: Skipping Rope | G193: E09 | H193: Rajesh Iyer | I193: Electronics | J193: South | K193: 2352.63 | L193: 2 | M193: 0.15 | N193: 4705.26 | O193: 3999.471 | P193: 2025-06-30 | Q193: Credit Card
A194: O0192 | B194: 45663 | C194: C019 | D194: Rohan Kumar | E194: P013 | F194: Wireless Mouse | G194: E01 | H194: Karan Mehta | I194: Home & Kitchen | J194: South | K194: 3981.64 | L194: 0 | M194: 0 | N194: 0 | O194: 0 | P194: 2025-01-10 | Q194: Debit Card | R194: Missing Quantity
A195: O0193 | B195: 45488 | C195: C026 | D195: Sneha Joshi | E195: P029 | F195: Non-stick Pan | G195: E09 | H195: Rajesh Iyer | I195: Sports | J195: West | K195: 1187.29 | L195: 4 | M195: 0 | N195: 4749.16 | O195: 4749.16 | P195: 2024-07-18 | Q195: Cash on Delivery
A196: O0194 | B196: 45395 | C196: C017 | D196: Amit Shah | E196: P032 | F196: Skipping Rope | G196: E02 | H196: Priya Nair | I196: Books | J196: West | K196: 605.26 | L196: 9 | M196: 0.2 | N196: 5447.34 | O196: 4357.872 | P196: 2024-04-22 | Q196: Cash on Delivery
A197: O0195 | B197: 45426 | C197: C039 | D197: Priya Desai | E197: P001 | F197: Self-Help Book | G197: E03 | H197: Rohit Sinha | I197: Electronics | J197: North | K197: 2352.63 | L197: 10 | M197: 0.05 | N197: 23526.3 | O197: 22349.985 | P197: 2024-05-17 | Q197: UPI
A198: O0196 | B198: 45461 | C198: C010 | D198: Aarav Singh | E198: P014 | F198: Wireless Mouse | G198: E03 | H198: Rohit Sinha | I198: Home & Kitchen | J198: South | K198: 733.33 | L198: 8 | M198: 0 | N198: 5866.64 | O198: 5866.64 | P198: 2024-06-25 | Q198: UPI
A199: O0197 | B199: 45746 | C199: C003 | D199: Kavya Shah | E199: P045 | F199: Blender | G199: E01 | H199: Karan Mehta | I199: Grocery | J199: North | K199: 3576.75 | L199: 10 | M199: 0 | N199: 35767.5 | O199: 35767.5 | P199: 2025-04-07 | Q199: Net Banking
A200: O0198 | B200: 45536 | C200: C060 | D200: Anjali Patel | E200: P035 | F200: Green Tea Pack | G200: E04 | H200: Fatima Sheikh | I200: Books | J200: North | K200: 1253.57 | L200: 5 | M200: 0.2 | N200: 6267.85 | O200: 5014.28 | P200: 2024-09-09 | Q200: Cash on Delivery
A201: O0199 | B201: 45743 | C201: C047 | D201: Riya Joshi | E201: P038 | F201: Comic Book | G201: E01 | H201: Karan Mehta | I201: Toys | J201: East | K201: 3205.14 | L201: 8 | M201: 0.2 | N201: 25641.12 | O201: 20512.896 | P201: 2025-04-01 | Q201: Net Banking
A202: O0200 | B202: 45832 | C202: C020 | D202: Priya Sharma | E202: P011 | F202: Remote Car | G202: E04 | H202: Fatima Sheikh | I202: Clothing | J202: North | K202: 1309.58 | L202: 7 | M202: 0 | N202: 9167.06 | O202: 9167.06 | P202: 2025-06-28 | Q202: Cash on Delivery
A203: O0201 | B203: 45345 | C203: C055 | D203: Meera Verma | E203: P016 | F203: Sports Jacket | G203: E02 | H203: Priya Nair | I203: Home & Kitchen | J203: West | K203: 3772.12 | L203: 0 | M203: 0.2 | N203: 0 | O203: 0 | P203: 2024-02-29 | Q203: Net Banking | R203: Missing Quantity
A204: O0202 | B204: 45419 | C204: C059 | D204: Sakshi Gupta | E204: P027 | F204: LED Lamp | G204: E02 | H204: Priya Nair | I204: Sports | J204: South | K204: 3128.51 | L204: 5 | M204: 0 | N204: 15642.55 | O204: 15642.55 | P204: 2024-05-10 | Q204: Debit Card
A205: O0203 | B205: 45817 | C205: C059 | D205: Sakshi Gupta | E205: P019 | F205: Cricket Bat | G205: E02 | H205: Priya Nair | I205: Beauty | J205: West | K205: 928.72 | L205: 3 | M205: 0.2 | N205: 2786.16 | O205: 2228.928 | P205: 2025-06-16 | Q205: UPI
A206: O0204 | B206: 45753 | C206: C012 | D206: Deepak Shah | E206: P002 | F206: Face Wash | G206: E02 | H206: Priya Nair | I206: Electronics | J206: West | K206: 991.59 | L206: 6 | M206: 0 | N206: 5949.54 | O206: 5949.54 | P206: 2025-04-13 | Q206: Debit Card
A207: O0205 | B207: 45806 | C207: C024 | D207: Anjali Joshi | E207: P037 | F207: Bluetooth Speaker | G207: E03 | H207: Rohit Sinha | I207: Toys | J207: West | K207: 588.75 | L207: 6 | M207: 0 | N207: 3532.5 | O207: 3532.5 | P207: 2025-06-05 | Q207: Cash on Delivery
A208: O0206 | B208: 45521 | C208: C024 | D208: Anjali Joshi | E208: P044 | F208: Building Blocks | G208: E03 | H208: Rohit Sinha | I208: Grocery | J208: South | K208: 620.89 | L208: 1 | M208: 0 | N208: 620.89 | O208: 620.89 | P208: 2024-08-19 | Q208: UPI
A209: O0207 | B209: 45432 | C209: C017 | D209: Amit Shah | E209: P020 | F209: Cooking Oil 1L | G209: E03 | H209: Rohit Sinha | I209: Beauty | J209: North | K209: 2359.5 | L209: 1 | M209: 0 | N209: 2359.5 | O209: 2359.5 | P209: 2024-05-28 | Q209: Debit Card
A210: O0208 | B210: 45751 | C210: C053 | D210: Deepak Joshi | E210: P020 | F210: Moisturizer | G210: E01 | H210: Karan Mehta | I210: Beauty | J210: West | K210: 2359.5 | L210: 10 | M210: 0 | N210: 23595 | O210: 23595 | P210: 2025-04-06 | Q210: Cash on Delivery
A211: O0209 | B211: 45512 | C211: C013 | D211: Kavya Sharma | E211: P039 | F211: Moisturizer | G211: E02 | H211: Priya Nair | I211: Toys | J211: East | K211: 2113.67 | L211: 3 | M211: 0.1 | N211: 6341.01 | O211: 5706.909 | P211: 2024-08-18 | Q211: Credit Card
A212: O0210 | B212: 45587 | C212: C023 | D212: Priya Joshi | E212: P044 | F212: Puzzle Set | G212: E02 | H212: Priya Nair | I212: Grocery | J212: West | K212: 620.89 | L212: 4 | M212: 0 | N212: 2483.56 | O212: 2483.56 | P212: 2024-10-24 | Q212: UPI
A213: O0211 | B213: 45721 | C213: C046 | D213: Rahul Mehta | E213: P039 | F213: Cooking Oil 1L | G213: E01 | H213: Karan Mehta | I213: Toys | J213: West | K213: 2113.67 | L213: 10 | M213: 0.05 | N213: 21136.7 | O213: 20079.865 | P213: 2025-03-07 | Q213: Debit Card
A214: O0212 | B214: 45308 | C214: C045 | D214: Aditya Joshi | E214: P041 | F214: Puzzle Set | G214: E01 | H214: Karan Mehta | I214: Toys | J214: North | K214: 136.91 | L214: 9 | M214: 0.1 | N214: 1232.19 | O214: 1108.971 | P214: 2024-01-21 | Q214: Cash on Delivery
A215: O0213 | B215: 45731 | C215: C024 | D215: Anjali Joshi | E215: P012 | F215: Board Game | G215: E09 | H215: Rajesh Iyer | I215: Clothing | J215: North | K215: 1559.65 | L215: 1 | M215: 0.1 | N215: 1559.65 | O215: 1403.685 | P215: 2025-03-21 | Q215: Net Banking
... A239: O0237 | B239: 45803 | C239: C055 | D239: Meera Verma | E239: P022 | F239: Remote Car | G239: E02 | H239: Priya Nair | I239: Beauty | J239: West | K239: 3414.07 | L239: 9 | M239: 0.05 | N239: 30726.63 | O239: 29190.299 | P239: 2025-06-04 | Q239: Cash on Delivery
A240: O0238 | B240: 45558 | C240: C002 | D240: Pooja Shah | E240: P006 | F240: Hair Serum | G240: E01 | H240: Karan Mehta | I240: Electronics | J240: South | K240: 2779.58 | L240: 0 | M240: 0 | N240: 0 | O240: 0 | P240: 2024-10-03 | Q240: Debit Card | R240: Missing Quantity
A241: O0239 | B241: 45496 | C241: C023 | D241: Priya Joshi | E241: P013 | F241: Power Bank | G241: E02 | H241: Priya Nair | I241: Home & Kitchen | J241: East | K241: 3981.64 | L241: 2 | M241: 0 | N241: 7963.28 | O241: 7963.28 | P241: 2024-07-25 | Q241: UPI
A242: O0240 | B242: 45747 | C242: C022 | D242: Rajesh Shah | E242: P010 | F242: Non-stick Pan | G242: E01 | H242: Karan Mehta | I242: Clothing | J242: South | K242: 1156.02 | L242: 2 | M242: 0.2 | N242: 2312.04 | O242: 1849.632 | P242: 2025-04-06 | Q242: Credit Card
A243: O0241 | B243: 45589 | C243: C015 | D243: Simran Joshi | E243: P034 | F243: Formal Shirt | G243: E02 | H243: Priya Nair | I243: Books | J243: North | K243: 2036.67 | L243: 5 | M243: 0.2 | N243: 10183.35 | O243: 8146.68 | P243: 2024-10-27 | Q243: Cash on Delivery
A244: O0242 | B244: 45812 | C244: C041 | D244: Deepak Mehta | E244: P039 | F244: Notebook Set | G244: E02 | H244: Priya Nair | I244: Toys | J244: North | K244: 2113.67 | L244: 4 | M244: 0 | N244: 8454.68 | O244: 8454.68 | P244: 2025-06-08 | Q244: UPI
A245: O0243 | B245: 45797 | C245: C033 | D245: Divya Singh | E245: P004 | F245: Puzzle Set | G245: E02 | H245: Priya Nair | I245: Electronics | J245: South | K245: 2184.51 | L245: 1 | M245: 0 | N245: 2184.51 | O245: 2184.51 | P245: 2025-05-29 | Q245: Debit Card
A246: O0244 | B246: 45424 | C246: C040 | D246: Aarav Kumar | E246: P010 | F246: Laptop Stand | G246: E09 | H246: Rajesh Iyer | I246: Clothing | J246: South | K246: 1156.02 | L246: 10 | M246: 0 | N246: 11560.2 | O246: 11560.2 | P246: 2024-05-14 | Q246: Debit Card
A247: O0245 | B247: 45782 | C247: C056 | D247: Mehul Mehta | E247: P039 | F247: Formal Shirt | G247: E09 | H247: Rajesh Iyer | I247: Toys | J247: West | K247: 2113.67 | L247: 9 | M247: 0.05 | N247: 19023.03 | O247: 18071.878 | P247: 2025-05-12 | Q247: UPI
A248: O0246 | B248: 45616 | C248: C043 | D248: Tanya Gupta | E248: P039 | F248: Puzzle Set | G248: E02 | H248: Priya Nair | I248: Toys | J248: South | K248: 2113.67 | L248: 2 | M248: 0.05 | N248: 4227.34 | O248: 4015.973 | P248: 2024-11-28 | Q248: UPI
A249: O0247 | B249: 45478 | C249: C018 | D249: Meera Verma | E249: P039 | F249: Puzzle Set | G249: E02 | H249: Priya Nair | I249: Toys | J249: West | K249: 2113.67 | L249: 3 | M249: 0.05 | N249: 6341.01 | O249: 6023.9595 | P249: 2024-07-14 | Q249: Credit Card
A250: O0248 | B250: 45822 | C250: C051 | D250: Deepak Verma | E250: P044 | F250: Puzzle Set | G250: E02 | H250: Priya Nair | I250: Grocery | J250: North | K250: 620.89 | L250: 3 | M250: 0 | N250: 1862.67 | O250: 1862.67 | P250: 2025-06-17 | Q250: Cash on Delivery
A251: O0249 | B251: 45522 | C251: C031 | D251: Sakshi Gupta | E251: P040 | F251: Cooking Oil 1L | G251: E09 | H251: Rajesh Iyer | I251: Toys | J251: West | K251: 1212.79 | L251: 6 | M251: 0.1 | N251: 7276.74 | O251: 6549.066 | P251: 2024-08-23 | Q251: Cash on Delivery
A252: O0250 | B252: 45493 | C252: C033 | D252: Divya Singh | E252: P043 | F252: Soft Toy | G252: E09 | H252: Rajesh Iyer | I252: Grocery | J252: South | K252: 2458.91 | L252: 9 | M252: 0 | N252: 22130.19 | O252: 22130.19 | P252: 2024-07-23 | Q252: Net Banking
... A351: O0347 | B351: 45392 | C351: C036 | D351: Aarav Desai | E351: P028 | F351: Self-Help Book | G351: E01 | H351: Karan Mehta | I351: Sports | J351: North | K351: 3493.54 | L351: 8 | M351: 0.2 | N351: 27948.32 | O351: 22358.656 | P351: 2024-04-16 | Q351: Cash on Delivery
A352: O0348 | B352: 45612 | C352: C018 | D352: Meera Verma | E352: P008 | F352: Perfume | G352: E04 | H352: Fatima Sheikh | I352: Clothing | J352: North | K352: 1498.91 | L352: 0 | M352: 0 | N352: 0 | O352: 0 | P352: 2024-11-26 | Q352: UPI | R352: Missing Quantity
A353: O0349 | B353: 45308 | C353: C036 | D353: Aarav Desai | E353: P022 | F353: Hoodie | G353: E02 | H353: Priya Nair | I353: Beauty | J353: East | K353: 3414.07 | L353: 5 | M353: 0.1 | N353: 17070.35 | O353: 15363.315 | P353: 2024-01-27 | Q353: Cash on Delivery
A354: O0350 | B354: 45448 | C354: C041 | D354: Deepak Mehta | E354: P028 | F354: Football | G354: E04 | H354: Fatima Sheikh | I354: Sports | J354: East | K354: 3493.54 | L354: 4 | M354: 0 | N354: 13974.16 | O354: 13974.16 | P354: 2024-06-09 | Q354: Net Banking
A355: O0351 | B355: 45543 | C355: C051 | D355: Deepak Verma | E355: P025 | F355: Denim Jeans | G355: E02 | H355: Priya Nair | I355: Sports | J355: South | K355: 4703.04 | L355: 8 | M355: 0.1 | N355: 37624.32 | O355: 33861.888 | P355: 2024-09-14 | Q355: Debit Card
A356: O0352 | B356: 45794 | C356: C002 | D356: Pooja Shah | E356: P038 | F356: Hair Serum | G356: E09 | H356: Rajesh Iyer | I356: Toys | J356: North | K356: 3205.14 | L356: 8 | M356: 0 | N356: 25641.12 | O356: 25641.12 | P356: 2025-05-23 | Q356: UPI
A357: O0353 | B357: 45792 | C357: C020 | D357: Priya Sharma | E357: P003 | F357: Football | G357: E04 | H357: Fatima Sheikh | I357: Electronics | J357: West | K357: 3550.89 | L357: 3 | M357: 0.1 | N357: 10652.67 | O357: 9587.403 | P357: 2025-05-16 | Q357: Credit Card
A358: O0354 | B358: 45341 | C358: C015 | D358: Simran Joshi | E358: P033 | F358: Yoga Mat | G358: E01 | H358: Karan Mehta | I358: Books | J358: North | K358: 2316.2 | L358: 1 | M358: 0.05 | N358: 2316.2 | O358: 2200.39 | P358: 2024-02-22 | Q358: Credit Card
A359: O0355 | B359: 45446 | C359: C046 | D359: Rahul Mehta | E359: P035 | F359: Remote Car | G359: E09 | H359: Rajesh Iyer | I359: Books | J359: East | K359: 1253.57 | L359: 1 | M359: 0 | N359: 1253.57 | O359: 1253.57 | P359: 2024-06-12 | Q359: Cash on Delivery
A360: O0356 | B360: 45353 | C360: C023 | D360: Priya Joshi | E360: P013 | F360: USB-C Charger | G360: E02 | H360: Priya Nair | I360: Home & Kitchen | J360: East | K360: 3981.64 | L360: 10 | M360: 0.15 | N360: 39816.4 | O360: 33843.94 | P360: 2024-03-12 | Q360: Debit Card
A361: O0357 | B361: 45308 | C361: C054 | D361: Simran Mehta | E361: P041 | F361: Cookbook | G361: E02 | H361: Priya Nair | I361: Toys | J361: East | K361: 136.91 | L361: 1 | M361: 0.1 | N361: 136.91 | O361: 123.219 | P361: 2024-01-26 | Q361: Credit Card
A362: O0358 | B362: 45309 | C362: C039 | D362: Priya Desai | E362: P016 | F362: Comic Book | G362: E03 | H362: Rohit Sinha | I362: Home & Kitchen | J362: South | K362: 3772.12 | L362: 9 | M362: 0.15 | N362: 33949.08 | O362: 28856.718 | P362: 2024-01-23 | Q362: Credit Card
A363: O0359 | B363: 45806 | C363: C034 | D363: Sakshi Verma | E363: P015 | F363: Non-stick Pan | G363: E09 | H363: Rajesh Iyer | I363: Home & Kitchen | J363: West | K363: 2849.53 | L363: 7 | M363: 0.2 | N363: 19946.71 | O363: 15957.368 | P363: 2025-06-01 | Q363: Credit Card
A364: O0360 | B364: 45828 | C364: C053 | D364: Deepak Joshi | E364: P008 | F364: Board Game | G364: E03 | H364: Rohit Sinha | I364: Clothing | J364: South | K364: 1498.91 | L364: 3 | M364: 0 | N364: 4496.73 | O364: 4496.73 | P364: 2025-06-24 | Q364: Cash on Delivery
... A399: O0395 | B399: 45367 | C399: C033 | D399: Divya Singh | E399: P010 | F399: Football | G399: E04 | H399: Fatima Sheikh | I399: Clothing | J399: East | K399: 1156.02 | L399: 8 | M399: 0.1 | N399: 9248.16 | O399: 8323.344 | P399: 2024-03-24 | Q399: Net Banking
A400: O0396 | B400: 45810 | C400: C008 | D400: Karan Verma | E400: P020 | F400: Remote Car | G400: E04 | H400: Fatima Sheikh | I400: Beauty | J400: South | K400: 2359.5 | L400: 0 | M400: 0.1 | N400: 0 | O400: 0 | P400: 2025-06-03 | Q400: Net Banking | R400: Missing Quantity
A401: O0397 | B401: 45379 | C401: C029 | D401: Pooja Kumar | E401: P040 | F401: Laptop Stand | G401: E03 | H401: Rohit Sinha | I401: Toys | J401: South | K401: 1212.79 | L401: 2 | M401: 0.2 | N401: 2425.58 | O401: 1940.464 | P401: 2024-04-01 | Q401: UPI
A402: O0398 | B402: 45337 | C402: C049 | D402: Arjun Kumar | E402: P023 | F402: Formal Shirt | G402: E01 | H402: Karan Mehta | I402: Beauty | J402: South | K402: 2405.98 | L402: 10 | M402: 0.15 | N402: 24059.8 | O402: 20450.83 | P402: 2024-02-22 | Q402: Debit Card
A403: O0399 | B403: 45400 | C403: C027 | D403: Sneha Gupta | E403: P010 | F403: Moisturizer | G403: E01 | H403: Karan Mehta | I403: Clothing | J403: North | K403: 1156.02 | L403: 1 | M403: 0 | N403: 1156.02 | O403: 1156.02 | P403: 2024-04-23 | Q403: Net Banking
A404: O0404 | B404: 45400 | C404: C027 | D404: Sneha Gupta | E404: P010 | F404: Sunscreen | G404: E01 | H404: Karan Mehta | I404: Clothing | J404: North | K404: 1156.02 | L404: 1 | M404: 0 | N404: 1156.02 | O404: 1156.02 | P404: 2024-04-23 | Q404: Net Banking
A405: O0400 | B405: 45823 | C405: C018 | D405: Meera Verma | E405: P035 | F405: Soft Toy | G405: E04 | H405: Fatima Sheikh | I405: Books | J405: North | K405: 1253.57 | L405: 9 | M405: 0.1 | N405: 11282.13 | O405: 10153.917 | P405: 2025-06-25 | Q405: Debit Card

Sheet Employees
A1: EmployeeID | B1: EmployeeName | C1: Department | D1: HireDate | E1: MonthlySalesTarget
A2: E01 | B2: Karan Mehta | C2: Sales | D2: 2024-01-04 | E2: 200000
A3: E02 | B3: Priya Nair | C3: Sales | D3: 2021-02-26 | E3: 100000
A4: E03 | B4: Rohit Sinha | C4: Sales | D4: 2022-06-19 | E4: 150000
A5: E04 | B5: Fatima Sheikh | C5: Sales | D5: 2024-04-04 | E5: 200000
A6: E05 | B6: Arjun Rao | C6: Support | D6: 2021-03-20 | E6: 100000
A7: E06 | B7: Sneha Kulkarni | C7: Support | D7: 2023-06-09 | E7: 200000
A8: E07 | B8: Vikas Yadav | C8: Marketing | D8: 2022-10-05 | E8: 250000
A9: E08 | B9: Neha Kapoor | C9: Marketing | D9: 2023-11-14 | E9: 100000
A10: E09 | B10: Rajesh Iyer | C10: Sales | D10: 2023-02-28 | E10: 150000
A11: E10 | B11: Divya Menon | C11: Support | D11: 2022-06-06 | E11: 100000

Sheet Pivot Tables
B3: Row Labels | C3: Sum of Revenue | E3: Row Labels | F3: Sum of Revenue | H3: Row Labels | I3: Sum of Revenue | K3: Row Labels | L3: Count of OrderID
B4: Jan | C4: 481369.82 | E4: Clothing | F4: 0.13828224 | H4: East | I4: 1114020.9 | K4: Cash on Delivery | L4: 0.20792079
B5: Feb | C5: 585532.08 | E5: Electronics | F5: 0.23080724 | H5: North | I5: 1134474.1 | K5: Credit Card | L5: 0.2029703
B6: Mar | C6: 579605.02 | E6: Grocery | F6: 0.19950351 | H6: South | I6: 1175918.4 | K6: Debit Card | L6: 0.22524752
B7: Apr | C7: 525950.07 | E7: Home & Kitchen | F7: 0.23137846 | H7: West | I7: 1231418 | K7: Net Banking | L7: 0.19059406
B8: May | C8: 627015.09 | E8: Sports | F8: 0.20002855 | H8: Grand Total | I8: 4655831.5 | K8: UPI | L8: 0.17326733
B9: Jun | C9: 335432.3 | E9: Grand Total | F9: 1 | K9: Grand Total | L9: 1
B10: Jul | C10: 290554.79
B11: Aug | C11: 236987.02
B12: Sep | C12: 253920.51
B13: Oct | C13: 213646.88
B14: Nov | C14: 338757.46
B15: Dec | C15: 187060.45
B16: Grand Total | C16: 4655831.5
B21: Customer Name | C21: Total Sales | E21: Row Labels | F21: Sum of Revenue | H21: Row Labels | I21: Count of OrderID
B22: Meera Verma | C22: 176894.67 | E22: USB-C Charger | F22: 213429.11 | H22: Fatima Sheikh | I22: 83
B23: Deepak Mehta | C23: 170943.3 | E23: LED Lamp | F23: 183252.53 | H23: Karan Mehta | I23: 69
B24: Karan Verma | C24: 155142.74 | E24: Football | F24: 181879.8 | H24: Priya Nair | I24: 94
B25: Sakshi Gupta | C25: 144965.31 | E25: Comic Book | F25: 178540.28 | H25: Rajesh Iyer | I25: 78
B26: Rajesh Shah | C26: 143431.34 | E26: Action Figure | F26: 174265.71 | H26: Grand Total | I26: 324
B27: Priya Joshi | C27: 137735.4 | E27: Power Bank | F27: 149959.77
B28: Riya Mehta | C28: 135656.78 | E28: Hair Serum | F28: 149351.46
B29: Yash Kumar | C29: 127699.13 | E29: Green Tea Pack | F29: 140263.45
B30: Kavya Sharma | C30: 127691.18 | E30: Hoodie | F30: 139777.29
B31: Rohan Kumar | C31: 125935.84 | E31: Honey Jar | F31: 139613.55
B32: Grand Total | C32: 1446095.7 | E32: Grand Total | F32: 1650333
B41: Total Revenue | C41: =TEXT(SUM(OrdersTable[[#All],[Revenue]]),"#,##0") -> 4,655,831
B43: Total Oreders | C43: =COUNTA(OrdersTable[OrderID]) -> 404
B45: Total Customers | C45: =COUNTA(OrdersTable[CustomerID]) -> 404
B47: Avgrage Order Value | C47: =TEXT(IFERROR(C41/C43,0),"#,##0") -> 11,524
B49: Total Qunatity Sold | C49: =TEXT(SUM(OrdersTable[Quantity]),"#,##0") -> 2,252

Sheet DashBoard
